{"alternate_locations": {"servers": [{"server": "dn790008.ca.archive.org", "dir": "/0/items/chnmany"}], "workable": [{"server": "dn790008.ca.archive.org", "dir": "/0/items/chnmany"}]}, "created": 1739344420, "d1": "ia601305.us.archive.org", "d2": "ia801305.us.archive.org", "dir": "/8/items/chnmany", "files": [{"name": "JPEG/chnmany_0001.jpg", "source": "original", "md5": "a3a3fdac2f364446b9a9b3c2d2bcba57", "mtime": "1051134937", "size": "3174770", "crc32": "dc60bc22", "sha1": "b216b1a2c96e73754a32006fc2627a05f8aa4d0d", "format": "JPEG", "rotation": "0"}, {"name": "JPEG/chnmany_0002.jpg", "source": "original", "md5": "7aa12efd050b5f9ecdb4d6d67ae6c7ec", "mtime": "1051134940", "size": "228393", "crc32": "1a8dd100", "sha1": "0066016059bbfab1e287c61ee514eaaed976bbd6", "format": "JPEG", "rotation": "0"}, {"name": "JPEG/chnmany_0003.jpg", "source": "original", "md5": "19f8a3edf9416c895e822576ef8b4707", "mtime": "1051134943", "size": "1201081", "crc32": "34088460", "sha1": "8cd80d041ab025dcee87762912a2172c15aefe48", "format": "JPEG", "rotation": "0"}, {"name": "JPEG/chnmany_0004.jpg", "source": "original", "md5": "87d911a1bed494c9cc44c58f76c9cd8c", "mtime": "1051134946", "size": "1253156", "crc32": "2423241", "sha1": "d10eab0349caf29daf746a2faccf6d568d9c32b3", "format": "JPEG", "rotation": "0"}, {"name": "JPEG/chnmany_0005.jpg", "source": "original", "md5": "0156010676cb2d44a7522ce41da74e06", "mtime": "1051134949", "size": "1513070", "crc32": "3f67ab16", "sha1": "5b583a539365cb35b79839b06fa90f307959ace6", "format": "JPEG", "rotation": "0"}, {"name": "JPEG/chnmany_0006.jpg", "source": "original", "md5": "8a061a5811188c92f289881c0896a137", "mtime": "1051134952", "size": "1248327", "crc32": "22af856b", "sha1": "94df7707763d7055ed483ace5c2c9237fc192804", "format": "JPEG", "rotation": "0"}, {"name": "JPEG/chnmany_0007.jpg", "source": "original", "md5": "21b6926026d44c51d32653e30a75ca4d", "mtime": "1051134955", "size": "1365289", "crc32": "30601ef5", "sha1": "9c6b75b3ae83be927f1c2b0f18257825e92b827d", "format": "JPEG", "rotation": "0"}, {"name": "JPEG/chnmany_0008.jpg", "source": "original", "md5": "ce6c58e22ba16ec2b51f8634626798d6", "mtime": "1051134958", "size": "3928708", "crc32": "55deb501", "sha1": "ea8241e1c2efe80a23d26d4e6e0d2438f603e498", "format": "JPEG", "rotation": "0"}, {"name": "JPEG/chnmany_0009.jpg", "source": "original", "md5": "d10c2c1f07caef17615a94ff09f071df", "mtime": "1051134961", "size": "3063994", "crc32": "518f532c", "sha1": "796ff0eef1b3f77e40af050b119c593d7524683e", "format": "JPEG", "rotation": "0"}, {"name": "JPEG/chnmany_0010.jpg", "source": "original", "md5": "699a1e2af86f850ea1dac17fefad737a", "mtime": "1051134964", "size": "4032222", "crc32": "4a4203bf", "sha1": "c438ecb836067aba7a277d5327ad833f0600ee9a", "format": "JPEG", "rotation": "0"}, {"name": "JPEG/chnmany_00100.jpg", "source": "original", "md5": "7dd40623ad8224cccd9e0601f28a37a8", "mtime": "1050104349", "size": "768374", "crc32": "d1ae3773", "sha1": "a5d734624d5abf2d2c40f2ca88d5937f3665dd7a", "format": "JPEG", "rotation": "0"}, {"name": "JPEG/chnmany_0011.jpg", "source": "original", "md5": "dbd587bb7293e2531b4aa7f3b5308769", "mtime": "1051134967", "size": "3487450", "crc32": "62404b28", "sha1": "3261e769b087f8cb77564c7926e4b555f902b61a", "format": "JPEG", "rotation": "0"}, {"name": "JPEG/chnmany_0012.jpg", "source": "original", "md5": "de799d7cd9bec75078f4efce5730331c", "mtime": "1051134969", "size": "3480455", "crc32": "14535cd2", "sha1": "5b0fa94bcf23e763c0a57892d6d10d7df42d613e", "format": "JPEG", "rotation": "0"}, {"name": "JPEG/chnmany_0013.jpg", "source": "original", "md5": "3761d57ba1cf787f4ce533955a0feb51", "mtime": "1051134972", "size": "2464745", "crc32": "a6cd37f8", "sha1": "3ede6d2c2c977c5d3e00ee2df54274d62d0613d6", "format": "JPEG", "rotation": "0"}, {"name": "JPEG/chnmany_0014.jpg", "source": "original", "md5": "0661237c973a1da29e2f5b7d5f07fa69", "mtime": "1051134975", "size": "2880569", "crc32": "7ef4a21c", "sha1": "315b379e1559b2ca106c1f85a8a78796b7ea27a3", "format": "JPEG", "rotation": "0"}, {"name": "JPEG/chnmany_0015.jpg", "source": "original", "md5": "e63a37476b74ce6420ff927eb032485b", "mtime": "1051134978", "size": "3595383", "crc32": "9876be93", "sha1": "77551f567b54034de790b97325defa58afb3e9fa", "format": "JPEG", "rotation": "0"}, {"name": "JPEG/chnmany_0016.jpg", "source": "original", "md5": "51d186c97ca71ad31ebf75c179e35698", "mtime": "1051134981", "size": "3424385", "crc32": "ec711ded", "sha1": "f26c1c9133e0b682152b310eb1bf7b8592fab4fb", "format": "JPEG", "rotation": "0"}, {"name": "JPEG/chnmany_0017.jpg", "source": "original", "md5": "3e52bb77507aa82143ef4591ac81bf8f", "mtime": "1051134984", "size": "2626536", "crc32": "c8da3155", "sha1": "5951141622b62bbdef344fa5f1148f12986edc19", "format": "JPEG", "rotation": "0"}, {"name": "JPEG/chnmany_0018.jpg", "source": "original", "md5": "0908df884a296485f7653e3447756d2a", "mtime": "1051134986", "size": "3207539", "crc32": "ca48d2a", "sha1": "cb83676b302515b239e4790c86bae0bd7044e546", "format": "JPEG", "rotation": "0"}, {"name": "JPEG/chnmany_0019.jpg", "source": "original", "md5": "a10aabc5fd6ae11657a545d5318722cd", "mtime": "1051134989", "size": "3295605", "crc32": "c6cafb89", "sha1": "8bbac0d2d1ce473f6f0b51be624044ab9389ea6d", "format": "JPEG", "rotation": "0"}, {"name": "JPEG/chnmany_0020.jpg", "source": "original", "md5": "135edd68cbe26de2388126dd327926fc", "mtime": "1051134992", "size": "2934726", "crc32": "7150f03e", "sha1": "aa406dc05c20b72dce94ed2dac260c0f46c0e339", "format": "JPEG", "rotation": "0"}, {"name": "JPEG/chnmany_0021.jpg", "source": "original", "md5": "dc04d057685caca3e245f35d78bd82cd", "mtime": "1051134995", "size": "2857693", "crc32": "a22e1dd6", "sha1": "9aeb02c7f901bf10fd504f0dd5860b204c4a5fe5", "format": "JPEG", "rotation": "0"}, {"name": "JPEG/chnmany_0022.jpg", "source": "original", "md5": "24a7209d69fb235d15337798ae0bc021", "mtime": "1051134998", "size": "3448119", "crc32": "132c4a5d", "sha1": "c4a486a754d79c6ca0d5a39cca98d8130930b3c6", "format": "JPEG", "rotation": "0"}, {"name": "JPEG/chnmany_0023.jpg", "source": "original", "md5": "85336091c299f33fde6c3ae8fa4aeddb", "mtime": "1051135000", "size": "3825728", "crc32": "dc8ede50", "sha1": "db350c4db493f34adbdc35ea70422e8b39cb8537", "format": "JPEG", "rotation": "0"}, {"name": "JPEG/chnmany_0024.jpg", "source": "original", "md5": "64d95ea17f3e8cd8e0a2d1f76f78e6dd", "mtime": "1051135003", "size": "3113552", "crc32": "4f2fbecf", "sha1": "bfb71bceca386b7844cb6cec8e8ffe8035d25102", "format": "JPEG", "rotation": "0"}, {"name": "JPEG/chnmany_0025.jpg", "source": "original", "md5": "e59b47c6393309c297178c449667a577", "mtime": "1051135005", "size": "2240052", "crc32": "e5544900", "sha1": "d2dcca41c0777ecb4f5a965dd0d2966073f2ff8b", "format": "JPEG", "rotation": "0"}, {"name": "JPEG/chnmany_0026.jpg", "source": "original", "md5": "e1f1abb52fc14237aa7fa9cfe8eb90dc", "mtime": "1051135008", "size": "4218169", "crc32": "2277f402", "sha1": "ea29262844218b5ba51d73d45dbd14e78cbb2f9e", "format": "JPEG", "rotation": "0"}, {"name": "JPEG/chnmany_0027.jpg", "source": "original", "md5": "01c9c1ea5253a8a54e56c389aaf9c86a", "mtime": "1051135011", "size": "3195346", "crc32": "6d73b7cc", "sha1": "036d82f5d3d1deecf35753e47261a0fcdc8e2819", "format": "JPEG", "rotation": "0"}, {"name": "JPEG/chnmany_0028.jpg", "source": "original", "md5": "2448e7d6fd6bbe633cd13910a86ebe76", "mtime": "1051135014", "size": "3987503", "crc32": "94f40da8", "sha1": "00cb480de82969bd63ce7a08aee197e2234afb43", "format": "JPEG", "rotation": "0"}, {"name": "JPEG/chnmany_0029.jpg", "source": "original", "md5": "e90471eb7044f27cf70397ae5d1b52dd", "mtime": "1051135016", "size": "3837772", "crc32": "939a2745", "sha1": "f3718fdcda80f7f8d8d1eed35829ef04307d2ace", "format": "JPEG", "rotation": "0"}, {"name": "JPEG/chnmany_0030.jpg", "source": "original", "md5": "08046f900221bcc40fee3631bf9958cc", "mtime": "1051135019", "size": "3476294", "crc32": "17889f8", "sha1": "3ff525fd53c1d380aea8403cef2282337e8d034a", "format": "JPEG", "rotation": "0"}, {"name": "JPEG/chnmany_0031.jpg", "source": "original", "md5": "d45b2bf5ed49b0b3d67046987717299d", "mtime": "1051135021", "size": "2948361", "crc32": "9d51847a", "sha1": "f8d6c1ead2813dcb0bf56f62d3d8175916c3ac4f", "format": "JPEG", "rotation": "0"}, {"name": "JPEG/chnmany_0032.jpg", "source": "original", "md5": "9942b5c867b40091d8f3f4a04add31e6", "mtime": "1051135023", "size": "2429343", "crc32": "622ccf12", "sha1": "89d610ba5ab478c9eecf98849e32dc91ade5191c", "format": "JPEG", "rotation": "0"}, {"name": "JPEG/chnmany_0033.jpg", "source": "original", "md5": "193e9c60e47aa35fccedeba32dac3e8f", "mtime": "1051135026", "size": "2985587", "crc32": "dc2dfdd2", "sha1": "064760af43a4697c2e77619f33e4c73f3e867a7a", "format": "JPEG", "rotation": "0"}, {"name": "JPEG/chnmany_0034.jpg", "source": "original", "md5": "01cdcce1c76475dbe31ad1948a8f746d", "mtime": "1051135028", "size": "2088565", "crc32": "647e310f", "sha1": "17ac1f5724c454ee8ec3c0dae234b7015644f2c4", "format": "JPEG", "rotation": "0"}, {"name": "JPEG/chnmany_0035.jpg", "source": "original", "md5": "8fd197168443a6fdd8e7e02a7587e9f3", "mtime": "1051135030", "size": "2382766", "crc32": "75fc449f", "sha1": "4a078d722fd1cf00fc4685faeb9d80e2140b3c1a", "format": "JPEG", "rotation": "0"}, {"name": "JPEG/chnmany_0036.jpg", "source": "original", "md5": "2a870aeef3532ff1e2ac92464c31cd00", "mtime": "1051135033", "size": "2612111", "crc32": "88fafba6", "sha1": "841ee9bd7435711942127f99697111bd9ea0a9f8", "format": "JPEG", "rotation": "0"}, {"name": "JPEG/chnmany_0037.jpg", "source": "original", "md5": "ac4d6b9bdafcdb788cb4b1d091d23fdd", "mtime": "1051135035", "size": "2323875", "crc32": "b78c01e2", "sha1": "13d64810f18e8c477e2bb0c9e274f513df875dd4", "format": "JPEG", "rotation": "0"}, {"name": "JPEG/chnmany_0038.jpg", "source": "original", "md5": "86bb87502acf5d4448a6350c6e5dbc69", "mtime": "1051135038", "size": "3093743", "crc32": "f820d6bd", "sha1": "5fa0d392b30c0ad900407cc783702c4d0c0dd8f4", "format": "JPEG", "rotation": "0"}, {"name": "JPEG/chnmany_0039.jpg", "source": "original", "md5": "b898c46d7812359c7e2ac4d3b5bcd930", "mtime": "1051135040", "size": "2477958", "crc32": "7a7da3ad", "sha1": "47071e7d2971ec3cd58e54d0bc35dc1aa478395c", "format": "JPEG", "rotation": "0"}, {"name": "JPEG/chnmany_0040.jpg", "source": "original", "md5": "498ba83d8e023aa659ebf3f0e3d8a04b", "mtime": "1051135042", "size": "610087", "crc32": "d73b241a", "sha1": "0f964d564c35c59f91324e88b57c2ec46873bbea", "format": "JPEG", "rotation": "0"}, {"name": "JPEG/chnmany_0041.jpg", "source": "original", "md5": "107c23e9e5e0a7c69ee9fcfe39dc7079", "mtime": "1051135046", "size": "3925959", "crc32": "499b2f04", "sha1": "e83dc55b5a971e26f88843b58bb4b61029c14d7f", "format": "JPEG", "rotation": "0"}, {"name": "JPEG/chnmany_0042.jpg", "source": "original", "md5": "e8ecec2dbfcf95c9f6ffce9335ed18bf", "mtime": "1051135049", "size": "4086300", "crc32": "ab1cdc9b", "sha1": "eb75cde02ade3c5c0af9afc4b4d203deaa6d4b66", "format": "JPEG", "rotation": "0"}, {"name": "JPEG/chnmany_0043.jpg", "source": "original", "md5": "8462cd69fbfeab74e1795c1baa6ab3a9", "mtime": "1051135052", "size": "3710311", "crc32": "34181239", "sha1": "529baa7034e4805dda13ae47a5dc4942d09542f2", "format": "JPEG", "rotation": "0"}, {"name": "JPEG/chnmany_0044.jpg", "source": "original", "md5": "9940cc9f04c570a6c7b428293bf2178d", "mtime": "1051135054", "size": "2738962", "crc32": "8b621b0a", "sha1": "2712908713186150ecbc79694e8b3a71f80b4c5f", "format": "JPEG", "rotation": "0"}, {"name": "JPEG/chnmany_0045.jpg", "source": "original", "md5": "84ae52753201cb56211ecc299ef797ab", "mtime": "1051135056", "size": "3439161", "crc32": "dd4111a", "sha1": "c9e8f12e99d9986db4b57329bcc21c9e531677c2", "format": "JPEG", "rotation": "0"}, {"name": "JPEG/chnmany_0046.jpg", "source": "original", "md5": "501fe7a48afb24a4dda3fb8b61d6b3e0", "mtime": "1051135059", "size": "3572503", "crc32": "42f72a0b", "sha1": "ef3105fe0a6775f59f10bb7a73c4a01f4f8844dc", "format": "JPEG", "rotation": "0"}, {"name": "JPEG/chnmany_0047.jpg", "source": "original", "md5": "9b607a9f8afe5d681d07652e5e08838c", "mtime": "1051135061", "size": "3188925", "crc32": "492d9c22", "sha1": "d5ec51aaee8c565f3a62549f74fafe03cbfadd9a", "format": "JPEG", "rotation": "0"}, {"name": "JPEG/chnmany_0048.jpg", "source": "original", "md5": "85b224d483bd9cfeacd9c3588485b337", "mtime": "1051135064", "size": "3160392", "crc32": "66767a7c", "sha1": "1b0fa1ff9c0381bbc549f5c91e40f0e4e681b0e8", "format": "JPEG", "rotation": "0"}, {"name": "JPEG/chnmany_0049.jpg", "source": "original", "md5": "e0acc57a43e48fdf0db72bffb749f1af", "mtime": "1051135066", "size": "2972634", "crc32": "b84b18ce", "sha1": "8e07d3765c4a6cb001edbc452230b3054ce0d9e0", "format": "JPEG", "rotation": "0"}, {"name": "JPEG/chnmany_0050.jpg", "source": "original", "md5": "3fabbbebe8078c88cd83bfbb1135594d", "mtime": "1051135069", "size": "2540880", "crc32": "12e495c2", "sha1": "2a116223055047305ee69e8cf2f6da63820bb453", "format": "JPEG", "rotation": "0"}, {"name": "JPEG/chnmany_0051.jpg", "source": "original", "md5": "757a2f2ef7c10c5da1ea9883926c7887", "mtime": "1051135071", "size": "2764675", "crc32": "731e23e7", "sha1": "ba3eb797f542266e31bde8085ea8f568e0ad1415", "format": "JPEG", "rotation": "0"}, {"name": "JPEG/chnmany_0052.jpg", "source": "original", "md5": "eb1274bd2877a521e70b21cd8284ab39", "mtime": "1051135074", "size": "1823145", "crc32": "ef04a378", "sha1": "d95f7d58ee2ed800f6b7e24f50b63ad0ffb20475", "format": "JPEG", "rotation": "0"}, {"name": "JPEG/chnmany_0053.jpg", "source": "original", "md5": "da00d9eee220bbd4e8de8cf98485af44", "mtime": "1051135076", "size": "1797082", "crc32": "e5ad593f", "sha1": "b9af83c6c8e3fb8a9e847325ed03394e02f7e5d3", "format": "JPEG", "rotation": "0"}, {"name": "JPEG/chnmany_0054.jpg", "source": "original", "md5": "faf7225e3f32d99301a4061b78b0b173", "mtime": "1051135078", "size": "2473067", "crc32": "4086a53a", "sha1": "9f5a11a3dc5133acfad06e0bc6fbad0e919f7786", "format": "JPEG", "rotation": "0"}, {"name": "JPEG/chnmany_0055.jpg", "source": "original", "md5": "12c3df7a743a7ed738674e3c73bbf531", "mtime": "1051135080", "size": "2929170", "crc32": "64451c27", "sha1": "7f62292a10293e93d029b7be6fcde03040231148", "format": "JPEG", "rotation": "0"}, {"name": "JPEG/chnmany_0056.jpg", "source": "original", "md5": "9f758215ee34d12b6dec9944374f93f3", "mtime": "1051135083", "size": "2475670", "crc32": "5a9422ee", "sha1": "f77522576d54c290238563312ad2269772ac40c0", "format": "JPEG", "rotation": "0"}, {"name": "JPEG/chnmany_0057.jpg", "source": "original", "md5": "996c9a797ba8f0464ea26fb5d3cef9c6", "mtime": "1051135085", "size": "2958905", "crc32": "6719e073", "sha1": "ef5bd2caa8fff5bb23bbcbc0c45fb6c8ea476036", "format": "JPEG", "rotation": "0"}, {"name": "JPEG/chnmany_0058.jpg", "source": "original", "md5": "9cc5413606228aa9bbf3caef99045fe0", "mtime": "1051135087", "size": "1647428", "crc32": "f7521025", "sha1": "e8afd71181694d934d3a769ac5e65679e664213d", "format": "JPEG", "rotation": "0"}, {"name": "JPEG/chnmany_0059.jpg", "source": "original", "md5": "13061a0b6b7e2c3319fa2cc8acc0b50a", "mtime": "1051135089", "size": "1878152", "crc32": "33401665", "sha1": "c3d1be3de53c8a8008e133f8b01f192400e4467d", "format": "JPEG", "rotation": "0"}, {"name": "JPEG/chnmany_0060.jpg", "source": "original", "md5": "ba98d2e5a21ec784998541ad0537f9c3", "mtime": "1051135091", "size": "2149250", "crc32": "63f98fd9", "sha1": "5de95476fb912cb30d4d47a890a25de71fa9d255", "format": "JPEG", "rotation": "0"}, {"name": "JPEG/chnmany_0061.jpg", "source": "original", "md5": "7c301de76a63842222eca863be6dece1", "mtime": "1051135094", "size": "2296796", "crc32": "84551847", "sha1": "c7103991cd1eb88c43acff21fc2f02bb9b43c877", "format": "JPEG", "rotation": "0"}, {"name": "JPEG/chnmany_0062.jpg", "source": "original", "md5": "8db12d3b1c39556d82089c72b72bdcf4", "mtime": "1051135096", "size": "1980923", "crc32": "7305f487", "sha1": "8690b2cd537ca0b6cf323bd0850097fa88287e82", "format": "JPEG", "rotation": "0"}, {"name": "JPEG/chnmany_0063.jpg", "source": "original", "md5": "00ac7908f355d58198343d68c7591898", "mtime": "1051135098", "size": "1940868", "crc32": "9955ea0c", "sha1": "d5ac4232d3cfb166b5b8e00969ac9d19e30e1784", "format": "JPEG", "rotation": "0"}, {"name": "JPEG/chnmany_0064.jpg", "source": "original", "md5": "1306d869612f0865724e594e24ba3f87", "mtime": "1051135100", "size": "2201825", "crc32": "e188f67c", "sha1": "f135d58e33d24e1d4906d10bb50b990bd3e18934", "format": "JPEG", "rotation": "0"}, {"name": "JPEG/chnmany_0065.jpg", "source": "original", "md5": "9e5ba5f6eaed1b936b3825b8ed19c94c", "mtime": "1051135102", "size": "2041051", "crc32": "539309a5", "sha1": "09c3b9b03c92a88c92c573e36acc4665cbaa0cd3", "format": "JPEG", "rotation": "0"}, {"name": "JPEG/chnmany_0066.jpg", "source": "original", "md5": "009926b684d9f440ca45cdb5853eafb9", "mtime": "1051135105", "size": "2465205", "crc32": "cf98f217", "sha1": "2c76d5ba8bd10105841f29e3fe701cd9f5403154", "format": "JPEG", "rotation": "0"}, {"name": "JPEG/chnmany_0067.jpg", "source": "original", "md5": "033f84303de97dfede8218aef06ff45b", "mtime": "1051135107", "size": "3010298", "crc32": "ab508fad", "sha1": "933d12e01f46b0e031b354f90ea230391fb6abc2", "format": "JPEG", "rotation": "0"}, {"name": "JPEG/chnmany_0068.jpg", "source": "original", "md5": "572d45e86a0f5cd9602d3d5f9bf6b598", "mtime": "1051135109", "size": "764289", "crc32": "cd64cba7", "sha1": "0c3372ac39028c8a401283a9150dec81f5a0284c", "format": "JPEG", "rotation": "0"}, {"name": "JPEG/chnmany_0069.jpg", "source": "original", "md5": "54abfc8ae603352816e4392fb33b6f11", "mtime": "1051135112", "size": "3885554", "crc32": "ee2909f", "sha1": "3a6dd840b37de6c66dcd5aecb01291268b7b476e", "format": "JPEG", "rotation": "0"}, {"name": "JPEG/chnmany_0070.jpg", "source": "original", "md5": "4443b1443e555df6c9f60d3acbabb2f8", "mtime": "1051135114", "size": "4298673", "crc32": "35f80c8d", "sha1": "a85d1444aa4aa682b1a84db57506714a6853c89b", "format": "JPEG", "rotation": "0"}, {"name": "JPEG/chnmany_0071.jpg", "source": "original", "md5": "637585f4f6699eaa994c79242651d4ee", "mtime": "1051135117", "size": "4291396", "crc32": "79a226dd", "sha1": "bc51f93aeaf09785c0009e5cf6b901716414262a", "format": "JPEG", "rotation": "0"}, {"name": "JPEG/chnmany_0072.jpg", "source": "original", "md5": "19c97c2e8b99e05391c28536b2831378", "mtime": "1051135119", "size": "2457382", "crc32": "673df9af", "sha1": "30f1602d0e37db8901c5e9624df6fd0d9b4d9332", "format": "JPEG", "rotation": "0"}, {"name": "JPEG/chnmany_0073.jpg", "source": "original", "md5": "8297972820afe6779920b4387d1d8d25", "mtime": "1051135122", "size": "3874403", "crc32": "edd49dd4", "sha1": "877a4f37bf499746e85838434ef9cb07fe7006ae", "format": "JPEG", "rotation": "0"}, {"name": "JPEG/chnmany_0074.jpg", "source": "original", "md5": "fe7a8e98bc79ddb192293368fac44fc2", "mtime": "1051135124", "size": "3947260", "crc32": "c7cb1348", "sha1": "65d9f1bf25bd9162b028c797aabdb8a09727ee20", "format": "JPEG", "rotation": "0"}, {"name": "JPEG/chnmany_0075.jpg", "source": "original", "md5": "d1009df9e384c57b9457831377560c3f", "mtime": "1051135127", "size": "4083766", "crc32": "e523bb67", "sha1": "506f1943b55ce65478db0c2f5e927682b3b19648", "format": "JPEG", "rotation": "0"}, {"name": "JPEG/chnmany_0076.jpg", "source": "original", "md5": "b34d9c818d4dc1cae9a21d4dea552f4d", "mtime": "1051135130", "size": "3011938", "crc32": "24d273f9", "sha1": "03d4839b9713a890ab59941b13c4eb26c81da9b8", "format": "JPEG", "rotation": "0"}, {"name": "JPEG/chnmany_0077.jpg", "source": "original", "md5": "115709f2574c759bc6f3747fa821ec06", "mtime": "1051135132", "size": "3782212", "crc32": "8558e6e0", "sha1": "bb1008f3ed5132465301a2414d72452a20503726", "format": "JPEG", "rotation": "0"}, {"name": "JPEG/chnmany_0078.jpg", "source": "original", "md5": "260e914ea3cf4dc3b737d7500225e503", "mtime": "1051135134", "size": "2555776", "crc32": "b57c33e1", "sha1": "b3e52054a9cbb53e1b92571cdfc3b36315b3455f", "format": "JPEG", "rotation": "0"}, {"name": "JPEG/chnmany_0079.jpg", "source": "original", "md5": "fd0ee868cfdb9cfb8084361e34718c8e", "mtime": "1051135137", "size": "3398852", "crc32": "b87dbf5b", "sha1": "785ba6daa7874713c9b2f48fed649fa64eeb8e3b", "format": "JPEG", "rotation": "0"}, {"name": "JPEG/chnmany_0080.jpg", "source": "original", "md5": "aebec0000c9012a422369a33fc5f3423", "mtime": "1051135139", "size": "2528232", "crc32": "90bc0684", "sha1": "f6b3b363da6d8a7b7e5596df003feddcf827b86a", "format": "JPEG", "rotation": "0"}, {"name": "JPEG/chnmany_0081.jpg", "source": "original", "md5": "00abe1ca294f9b6d40de7bf4f5e5b73b", "mtime": "1051135141", "size": "2281882", "crc32": "5f3dfb61", "sha1": "510c8159646c9ff4b98f1092a99083b3edfaac31", "format": "JPEG", "rotation": "0"}, {"name": "JPEG/chnmany_0082.jpg", "source": "original", "md5": "a7b0567199af220a8eafdbfb555c6e12", "mtime": "1051135144", "size": "2334534", "crc32": "31ec6f83", "sha1": "47d3e1ed03d423b02356db1d1b62ba6aa3b5dc42", "format": "JPEG", "rotation": "0"}, {"name": "JPEG/chnmany_0083.jpg", "source": "original", "md5": "1c7ba54610e6edee185e52e4985ebe70", "mtime": "1051135146", "size": "3237062", "crc32": "5ca1c056", "sha1": "e7f291b3ccb77ac563aee1f3a1434fc9ffe412ab", "format": "JPEG", "rotation": "0"}, {"name": "JPEG/chnmany_0084.jpg", "source": "original", "md5": "6e77c815f51c7cad98cf3005b11955d0", "mtime": "1051135148", "size": "2503446", "crc32": "2e813028", "sha1": "6daec93106512b92118f43d366244053d9942f54", "format": "JPEG", "rotation": "0"}, {"name": "JPEG/chnmany_0085.jpg", "source": "original", "md5": "428dae9a46d4e20503ad15f5f52ec5e5", "mtime": "1051135151", "size": "3440878", "crc32": "9d82e906", "sha1": "125fb088514ff6f09752e2b8e5ca3894fc84ccb6", "format": "JPEG", "rotation": "0"}, {"name": "JPEG/chnmany_0086.jpg", "source": "original", "md5": "b23419afece0240b7a2c7a2007a858d5", "mtime": "1051135153", "size": "2713526", "crc32": "253368a9", "sha1": "2facb8131de74bb5ce374af29fda30602b0e3033", "format": "JPEG", "rotation": "0"}, {"name": "JPEG/chnmany_0087.jpg", "source": "original", "md5": "ff7500c69d39b32dc1646be033344d0d", "mtime": "1051135155", "size": "3652111", "crc32": "e1cb7472", "sha1": "5d4c0e6c0330e1a8e2a6c6d5a8d03232d35f2daa", "format": "JPEG", "rotation": "0"}, {"name": "JPEG/chnmany_0088.jpg", "source": "original", "md5": "ca52ab56c37ca6ed20cc24953e5f46b5", "mtime": "1051135158", "size": "2688741", "crc32": "63bd881c", "sha1": "6d3c4d06465f4b7618b1367f35754021c297e9d3", "format": "JPEG", "rotation": "0"}, {"name": "JPEG/chnmany_0089.jpg", "source": "original", "md5": "fef47e6fe90e01a45f418ba268b21be9", "mtime": "1051135160", "size": "3615436", "crc32": "1252bd12", "sha1": "8132380897746f00aba80e9cd5794eeace54765f", "format": "JPEG", "rotation": "0"}, {"name": "JPEG/chnmany_0090.jpg", "source": "original", "md5": "9c87fcb30f8380c89b425312ce9654c2", "mtime": "1051135163", "size": "2617515", "crc32": "48cb9b3b", "sha1": "f07087771f448ad2e7cfd39fe8be34a76822c347", "format": "JPEG", "rotation": "0"}, {"name": "JPEG/chnmany_0091.jpg", "source": "original", "md5": "5c267679602b708ecdfab74c8cae5708", "mtime": "1051135165", "size": "3600604", "crc32": "63814057", "sha1": "40d481cb0a0ba53df7199db4c4072081867089a9", "format": "JPEG", "rotation": "0"}, {"name": "JPEG/chnmany_0092.jpg", "source": "original", "md5": "d76a527dc2a1eee085afe3092c743e8d", "mtime": "1051135168", "size": "3172918", "crc32": "635e335c", "sha1": "e336f0a88380b711a751e63c201d554a44c3f2b1", "format": "JPEG", "rotation": "0"}, {"name": "JPEG/chnmany_0093.jpg", "source": "original", "md5": "60e6334e07234550e08b869c35770fc6", "mtime": "1051135170", "size": "3170157", "crc32": "502d76ac", "sha1": "4c37d37fa128ee4c96a9e2271fd1b7a29d7b59f1", "format": "JPEG", "rotation": "0"}, {"name": "JPEG/chnmany_0094.jpg", "source": "original", "md5": "f7d02b51129c93a8f7017424755b5e1c", "mtime": "1051135173", "size": "3444284", "crc32": "1385b713", "sha1": "9904496a314dc7bd2b53ed39b3df540fe5c82e27", "format": "JPEG", "rotation": "0"}, {"name": "JPEG/chnmany_0095.jpg", "source": "original", "md5": "a61675a74a93f1a6fe9e303572a5d2f2", "mtime": "1051135175", "size": "3365366", "crc32": "a899cd20", "sha1": "3b18ac6b56f84129e553e20c0a0855322e733ebb", "format": "JPEG", "rotation": "0"}, {"name": "JPEG/chnmany_0096.jpg", "source": "original", "md5": "8afb68aacd81c7cdf97a0c93fb3b0c9e", "mtime": "1051135178", "size": "3862821", "crc32": "fe92ee00", "sha1": "0a42f3c91b7024d6b567baaf4da8687844a75133", "format": "JPEG", "rotation": "0"}, {"name": "JPEG/chnmany_0097.jpg", "source": "original", "md5": "27bbc8a56473a00de3cc3e303da5d9cc", "mtime": "1051135180", "size": "3246084", "crc32": "9e93e099", "sha1": "5dd3b68b16abd27aa0dc724f16d47f5612b164fa", "format": "JPEG", "rotation": "0"}, {"name": "JPEG/chnmany_0098.jpg", "source": "original", "md5": "e6c31e81ca05f3fa89f2c440e6b24212", "mtime": "1051135183", "size": "2628165", "crc32": "9af74e76", "sha1": "42db11d65015b2991aee731fa980b813df84682a", "format": "JPEG", "rotation": "0"}, {"name": "JPEG/chnmany_0099.jpg", "source": "original", "md5": "55f7586377ef3735f77f3f6bd94e3a70", "mtime": "1051135186", "size": "3818507", "crc32": "662c1d6a", "sha1": "1c5de349f921255604902db2cdc6af387a93ec38", "format": "JPEG", "rotation": "0"}, {"name": "JPEG/chnmany_0100.jpg", "source": "original", "md5": "cb646db8d30b0660b33c02700b4be28b", "mtime": "1051135188", "size": "739795", "crc32": "15a76fc2", "sha1": "21adc063a8f0a6a0d620ab7406dffbae4f92b541", "format": "JPEG", "rotation": "0"}, {"name": "JPEG/chnmany_0101.jpg", "source": "original", "md5": "692a07bb5ea6a4fa7a571a8f6f434330", "mtime": "1051135190", "size": "2075035", "crc32": "71c5c703", "sha1": "adb5e1fdb9109d3bace081820e98350687f893b0", "format": "JPEG", "rotation": "0"}, {"name": "JPEG/chnmany_0102.jpg", "source": "original", "md5": "b404b1bd2ea942fd863d1079a2d2f49d", "mtime": "1051135192", "size": "1433565", "crc32": "b5ff6067", "sha1": "4eee29587225d4588743df3a98f16d482738ad43", "format": "JPEG", "rotation": "0"}, {"name": "JPEG/chnmany_0103.jpg", "source": "original", "md5": "513e3e5538f3d0d764101a3cd8377bfa", "mtime": "1051135194", "size": "269293", "crc32": "d30ee79d", "sha1": "90fd70718a6d304e0827315b8a7529df22ce8b49", "format": "JPEG", "rotation": "0"}, {"name": "JPEG/chnmany_0104.jpg", "source": "original", "md5": "26ecbf5558437a5cc1ad4282e9a7399d", "mtime": "1051135197", "size": "3082154", "crc32": "d6308a37", "sha1": "6d5189319dc54437ddb1ee7801aface2e429ae14", "format": "JPEG", "rotation": "0"}, {"name": "PTIFF/chnmany_0001.tif", "source": "original", "md5": "58fd69f64ed167fd8ad6ad42ba81ba33", "mtime": "1051130945", "size": "16391624", "crc32": "a3f01911", "sha1": "e11f56e24726bdbda573203e509e02190ff170f9", "format": "TIFF"}, {"name": "PTIFF/chnmany_0002.tif", "source": "original", "md5": "7cfeb00c273325e21f8d92f657710503", "mtime": "1051130933", "size": "15561708", "crc32": "f0f5793b", "sha1": "263b78cadb735ac390b43633df7d8b0a897449d3", "format": "TIFF"}, {"name": "PTIFF/chnmany_0003.tif", "source": "original", "md5": "cb850dda65a12714887c9c742ffddc67", "mtime": "1051130924", "size": "15665512", "crc32": "e652bcbd", "sha1": "1b0fcd599180200d1d6c672758b997c04085d324", "format": "TIFF"}, {"name": "PTIFF/chnmany_0004.tif", "source": "original", "md5": "1bc2d821960c205968fea445af291b04", "mtime": "1050100723", "size": "16299552", "crc32": "873fa084", "sha1": "8fbc173c6dc0e5277dd9680691793786fb8859df", "format": "TIFF"}, {"name": "PTIFF/chnmany_0005.tif", "source": "original", "md5": "f03d6f3dfa1589934436028b1ffda5d3", "mtime": "1050100729", "size": "16104548", "crc32": "213ff228", "sha1": "e3a18bdc7eb8e5d1615db0626ed20dfacd083001", "format": "TIFF"}, {"name": "PTIFF/chnmany_0006.tif", "source": "original", "md5": "ba964a68a85705be749f9c4fe061bf98", "mtime": "1050100736", "size": "16102760", "crc32": "9589c58f", "sha1": "8d7a2dd1c6bc982cf1cd5fc076ac4d1b8a334224", "format": "TIFF"}, {"name": "PTIFF/chnmany_0007.tif", "source": "original", "md5": "2cba195e583f23d6f8d2e91bf45104bb", "mtime": "1051130829", "size": "15329040", "crc32": "18f9eff4", "sha1": "1bc78f81f3e20a2558916fc83e78bd6be4ef6bb4", "format": "TIFF"}, {"name": "PTIFF/chnmany_0008.tif", "source": "original", "md5": "c6d7f57cebbc057632aaa9ddedf46f9c", "mtime": "1051130820", "size": "15231588", "crc32": "88d44b4c", "sha1": "4d0c4aae271330cb8b53e5217139704e92ec0046", "format": "TIFF"}, {"name": "PTIFF/chnmany_0009.tif", "source": "original", "md5": "435cf6ecec41f425f3f55faf96161aa4", "mtime": "1051130800", "size": "15590548", "crc32": "ce762878", "sha1": "50fa6f5baf2d5c12359f889be4b20bde98e4dc1c", "format": "TIFF"}, {"name": "PTIFF/chnmany_0010.tif", "source": "original", "md5": "622ca2ace63c2eb7c2982f29a111006b", "mtime": "1051130791", "size": "15269684", "crc32": "a4707740", "sha1": "f1ffb6894fff2547a9fe95326ee9032e59c625cf", "format": "TIFF"}, {"name": "PTIFF/chnmany_0011.tif", "source": "original", "md5": "8565a4f4b35e5638cc33bee1dd0dbc63", "mtime": "1051131325", "size": "14977760", "crc32": "dddc6f0c", "sha1": "85f77d1c082e7dd5d519a69cbe18c3f21e0ba6f9", "format": "TIFF"}, {"name": "PTIFF/chnmany_0012.tif", "source": "original", "md5": "7424610ae6f488773db56f77db230c4b", "mtime": "1051131316", "size": "15281444", "crc32": "cd3e8c0c", "sha1": "e84d9e21d57b890d99baf18ad71878daf4c33ac9", "format": "TIFF"}, {"name": "PTIFF/chnmany_0013.tif", "source": "original", "md5": "9ab73bc3805c138d81d2d7da3503dc1a", "mtime": "1051131309", "size": "15099484", "crc32": "253e52f5", "sha1": "48b8a5aa42bad2640f2a0c2310d7993eb7fb1c64", "format": "TIFF"}, {"name": "PTIFF/chnmany_0014.tif", "source": "original", "md5": "5f8cba1fccd625c4834fdead63b91af1", "mtime": "1051131283", "size": "15122032", "crc32": "0861731c", "sha1": "6a0d0aff07b9a4110f717984ed7a0c9c073f0c83", "format": "TIFF"}, {"name": "PTIFF/chnmany_0015.tif", "source": "original", "md5": "049fe1a6d87f4af3896e5b406c9c7028", "mtime": "1051131275", "size": "15017860", "crc32": "f34023cf", "sha1": "84a4c7120dd4e5f3b04701c223d656bb8ce9069d", "format": "TIFF"}, {"name": "PTIFF/chnmany_0016.tif", "source": "original", "md5": "4cfb8c2e5cf51f229b1e79084a73f728", "mtime": "1051131267", "size": "15238780", "crc32": "5d51227c", "sha1": "b15e4086ea33473a78ec8c5c5cfc3a7373ca6fdc", "format": "TIFF"}, {"name": "PTIFF/chnmany_0017.tif", "source": "original", "md5": "88b4b6912dae07c2b4eb029b88d49cb6", "mtime": "1051131230", "size": "14655664", "crc32": "a8c368a1", "sha1": "5846fac8a96ba80a9ab48e273dbbe9bb196676ef", "format": "TIFF"}, {"name": "PTIFF/chnmany_0018.tif", "source": "original", "md5": "e96b1245af34f5ef6ecfd0a5e84f5d8d", "mtime": "1051131221", "size": "14946776", "crc32": "a4f425a7", "sha1": "c62d42429d2ce0e5667e819ee2fc8425936b1d1c", "format": "TIFF"}, {"name": "PTIFF/chnmany_0019.tif", "source": "original", "md5": "783d0e1676d1976aa6fc6023bbdc260d", "mtime": "1051131213", "size": "15179128", "crc32": "39a90b11", "sha1": "a5eeb70a99a1bbf7a7ea3f86226a3905a2ac8865", "format": "TIFF"}, {"name": "PTIFF/chnmany_0020.tif", "source": "original", "md5": "c3271dc41c87c73e58f9981b07ad020a", "mtime": "1051131203", "size": "15147820", "crc32": "c2594326", "sha1": "34a25e4add9ae507291e9c938ec5b213ea4b1506", "format": "TIFF"}, {"name": "PTIFF/chnmany_0021.tif", "source": "original", "md5": "f8da949e3c32dd39d5ca63a60f5b9f62", "mtime": "1050100876", "size": "15681032", "crc32": "f8ced4ba", "sha1": "98ad0cbb59ddce0a4938d7056b075bfe2f9471da", "format": "TIFF"}, {"name": "PTIFF/chnmany_0022.tif", "source": "original", "md5": "c63913f993e28a5ff71cd09ceaaa8956", "mtime": "1051131488", "size": "14947600", "crc32": "80fb4544", "sha1": "da3800798a840df7d66da39710f12e11a4216c9c", "format": "TIFF"}, {"name": "PTIFF/chnmany_0023.tif", "source": "original", "md5": "5abfc517fdf062d9aa800b2cb6cb1d50", "mtime": "1051131479", "size": "15003884", "crc32": "16679747", "sha1": "2cc6ac9755c67f049ecbdd2643b1634e7b90b2c5", "format": "TIFF"}, {"name": "PTIFF/chnmany_0024.tif", "source": "original", "md5": "2ffa3eda3c9549152cb0f108bece2547", "mtime": "1051131470", "size": "14560044", "crc32": "5b02f1c3", "sha1": "f4fb0db60a73f19e2ff7bf47535768587b9bc490", "format": "TIFF"}, {"name": "PTIFF/chnmany_0025.tif", "source": "original", "md5": "9726e092f5ac2ac89cfde7386e06c5a9", "mtime": "1051131456", "size": "14768088", "crc32": "f6aa4b22", "sha1": "f1dda25e4679938faea09a55ce92c358d537a443", "format": "TIFF"}, {"name": "PTIFF/chnmany_0026.tif", "source": "original", "md5": "f1b1d0859d320f67373960a70d1619fa", "mtime": "1051131448", "size": "14873740", "crc32": "622fe51e", "sha1": "5612aaa5fef9eb70576896d5f94abfd27707b71a", "format": "TIFF"}, {"name": "PTIFF/chnmany_0027.tif", "source": "original", "md5": "0952d39854f1dbc6b73d5ff4184d44ff", "mtime": "1051131441", "size": "14896496", "crc32": "90e395c6", "sha1": "8bbe76e5d44723f161525f1e6ea07cd8fea603c6", "format": "TIFF"}, {"name": "PTIFF/chnmany_0028.tif", "source": "original", "md5": "452d80d04401829077cbb7702be2f034", "mtime": "1051131433", "size": "14749176", "crc32": "014ddb78", "sha1": "d6599b6ff7c611e201f6c382bc6d61777af4af11", "format": "TIFF"}, {"name": "PTIFF/chnmany_0029.tif", "source": "original", "md5": "5758637b9dc4c5dd80aefc969db51f28", "mtime": "1051131426", "size": "14768944", "crc32": "c3dddd97", "sha1": "7be11708bfe487ce30d53cf56754d7fab7d82dee", "format": "TIFF"}, {"name": "PTIFF/chnmany_0030.tif", "source": "original", "md5": "61259de0f8aba93094d40d88b3d15a12", "mtime": "1051131418", "size": "14687620", "crc32": "4824f045", "sha1": "42185cf5f1b64c314eee71f9e4e1b7b51192f54d", "format": "TIFF"}, {"name": "PTIFF/chnmany_0031.tif", "source": "original", "md5": "d2186ec75efb4e77618364e45168e5bd", "mtime": "1051131396", "size": "14305336", "crc32": "2298a35e", "sha1": "c0b9f6c3a5fbfd7918cc33f79b73fca9fab327b9", "format": "TIFF"}, {"name": "PTIFF/chnmany_0032.tif", "source": "original", "md5": "3bbf964fb007997cc00f5e1bfee5b97b", "mtime": "1051131388", "size": "13944820", "crc32": "d9197c14", "sha1": "831e47641e734097677c7d8bf015f767490d4d8e", "format": "TIFF"}, {"name": "PTIFF/chnmany_0033.tif", "source": "original", "md5": "0723a9ed84e791d5ab9d7db595b4e63f", "mtime": "1051131817", "size": "13991260", "crc32": "af7fde9e", "sha1": "7830abe3667723d04badc4690b7d717ee5d76199", "format": "TIFF"}, {"name": "PTIFF/chnmany_0034.tif", "source": "original", "md5": "2dc60bd0127ba7c39839486e8959f43b", "mtime": "1051131807", "size": "13489296", "crc32": "2926a6c3", "sha1": "285ab56fc53fd93cdedee14e13f4a724d6d333c8", "format": "TIFF"}, {"name": "PTIFF/chnmany_0035.tif", "source": "original", "md5": "e181ac644963262d07c2919af2740e43", "mtime": "1051131778", "size": "13976192", "crc32": "6ce401e4", "sha1": "4cd076a34ee7dc8f15b571d059ef1f817e732779", "format": "TIFF"}, {"name": "PTIFF/chnmany_0036.tif", "source": "original", "md5": "d0582a2504dd4972a39aa585bcd71721", "mtime": "1051131768", "size": "13800708", "crc32": "2858baa5", "sha1": "41aa35f9c1043664bfc863db6eee8fb235ccc0b9", "format": "TIFF"}, {"name": "PTIFF/chnmany_0037.tif", "source": "original", "md5": "07168c49f27d0e7e3f46483be15d7129", "mtime": "1051131737", "size": "13941360", "crc32": "21e0ca1d", "sha1": "8124537439172e999cf054188d3feb9c5b985830", "format": "TIFF"}, {"name": "PTIFF/chnmany_0038.tif", "source": "original", "md5": "90d4cf42ba33920d13ff8517f9872021", "mtime": "1051131704", "size": "14676040", "crc32": "89081ab0", "sha1": "e09e530329108334a14031ccc8b82133830ea54a", "format": "TIFF"}, {"name": "PTIFF/chnmany_0039.tif", "source": "original", "md5": "26431f02a3980298736256326dfe37ef", "mtime": "1050100982", "size": "16195000", "crc32": "a206153a", "sha1": "a489f779a028ac04ff02fa46752a9c559ef0c745", "format": "TIFF"}, {"name": "PTIFF/chnmany_0040.tif", "source": "original", "md5": "8a5db4805d5ca0fe7f6062fbed1f54ad", "mtime": "1050100985", "size": "15543820", "crc32": "f930519b", "sha1": "45be4194d3027d2125aaddb6678728c5e075a387", "format": "TIFF"}, {"name": "PTIFF/chnmany_0041.tif", "source": "original", "md5": "542fd032aecdc52e1a46a9a1cb45f9a3", "mtime": "1050101467", "size": "16197160", "crc32": "5ff2faf6", "sha1": "0999bc2a5cedf043c4fc90efd980281670e5ba7b", "format": "TIFF"}, {"name": "PTIFF/chnmany_0042.tif", "source": "original", "md5": "e97b3fff58c23af7caecb4fb5904ec0d", "mtime": "1051131689", "size": "14644520", "crc32": "eb6e456a", "sha1": "b7c658aff94a94be65a0ec254482964125825e17", "format": "TIFF"}, {"name": "PTIFF/chnmany_0043.tif", "source": "original", "md5": "8fbab91a8a79759b26de7f3d6a4f5d7d", "mtime": "1050101477", "size": "16272784", "crc32": "78ce64c5", "sha1": "cccb64f604e9ca1a7b0666b2db18fd1f9cd426c1", "format": "TIFF"}, {"name": "PTIFF/chnmany_0044.tif", "source": "original", "md5": "0cdeb495bfc8efc2167c2d121b11180f", "mtime": "1051132402", "size": "14622020", "crc32": "e5c428d6", "sha1": "47ef91e6d9a51606b98f9ae70f144067d71c3356", "format": "TIFF"}, {"name": "PTIFF/chnmany_0045.tif", "source": "original", "md5": "c84d0bc778ae023934b26a2035f45228", "mtime": "1051132394", "size": "15081444", "crc32": "592e5394", "sha1": "2eba722125791bc5331c7900399ab531ab9c3740", "format": "TIFF"}, {"name": "PTIFF/chnmany_0046.tif", "source": "original", "md5": "dc6ca34e1e769ab30611cf44a4ba70d7", "mtime": "1051132384", "size": "14549144", "crc32": "eb0316a9", "sha1": "c26e6ba6c1320f366a092e9f544574d0c9c5d71e", "format": "TIFF"}, {"name": "PTIFF/chnmany_0047.tif", "source": "original", "md5": "3e3e267e5c85ba61f2b7c4cae234af88", "mtime": "1051132297", "size": "14916968", "crc32": "b53ff444", "sha1": "feb7e8351cf78b5052e3022816f0b0f5c15d53ed", "format": "TIFF"}, {"name": "PTIFF/chnmany_0048.tif", "source": "original", "md5": "e7091ee780092c66dec7acbd889bf5ee", "mtime": "1051132283", "size": "14224328", "crc32": "38efc0c0", "sha1": "aab3e02b82b38d7e485d0b90a5fa88e91c2b5d21", "format": "TIFF"}, {"name": "PTIFF/chnmany_0049.tif", "source": "original", "md5": "4bfd63f7ff6a6fc6581dbabb6d30c565", "mtime": "1051132247", "size": "14927008", "crc32": "e64dcc32", "sha1": "0507846753553195def0112778a579f76930986e", "format": "TIFF"}, {"name": "PTIFF/chnmany_0050.tif", "source": "original", "md5": "8f85b6861aa41ba83ab938316624206a", "mtime": "1051131980", "size": "14056180", "crc32": "defdc720", "sha1": "a94269412f041d4b1acbd021a84c70247f8c667b", "format": "TIFF"}, {"name": "PTIFF/chnmany_0051.tif", "source": "original", "md5": "d1ae3a9a7f6c8fe6b2b17803dcca62f0", "mtime": "1050101978", "size": "16272248", "crc32": "2308eb86", "sha1": "7155666f28e44d853421193293b3773d278c33f9", "format": "TIFF"}, {"name": "PTIFF/chnmany_0052.tif", "source": "original", "md5": "789af48684bb1c782b9c2e01ac88255b", "mtime": "1051131950", "size": "14448968", "crc32": "48256a49", "sha1": "857f94b6175d78370297b8d8aa9fe45a1a11aefc", "format": "TIFF"}, {"name": "PTIFF/chnmany_0053.tif", "source": "original", "md5": "ea60f2667774897f4dcdd274705d20cb", "mtime": "1051131928", "size": "14473432", "crc32": "e881ad44", "sha1": "6e47e74bd08dc531835de14ddfc150aef3294944", "format": "TIFF"}, {"name": "PTIFF/chnmany_0054.tif", "source": "original", "md5": "bc12658c9a6c8e38b1c14b5ce6ce04b3", "mtime": "1051131871", "size": "14307636", "crc32": "fbe8a8f9", "sha1": "4e4002600e04438daadd21c78537f733be6a2caa", "format": "TIFF"}, {"name": "PTIFF/chnmany_0055.tif", "source": "original", "md5": "0a592c5d4d6eaa79490b5da4b77b9dc8", "mtime": "1051132572", "size": "15116480", "crc32": "19613ecd", "sha1": "c1a57382ba3dfc592aa45f10c6044e57654dc9ad", "format": "TIFF"}, {"name": "PTIFF/chnmany_0056.tif", "source": "original", "md5": "aa5d19298d659f98df11e08a10914257", "mtime": "1051132883", "size": "14066304", "crc32": "5fb255f2", "sha1": "81f3eab795b40da8e2e5bbd6c84ab99dbb9f2581", "format": "TIFF"}, {"name": "PTIFF/chnmany_0057.tif", "source": "original", "md5": "375dd1b7235b56222b39c825bd48bee3", "mtime": "1051132862", "size": "14616084", "crc32": "d14852df", "sha1": "e77e9d2265277490857e42506bd15cbf1e72cf07", "format": "TIFF"}, {"name": "PTIFF/chnmany_0058.tif", "source": "original", "md5": "376556c38db54dfd2f8a44164c581a00", "mtime": "1051132802", "size": "13801624", "crc32": "6a1c28b0", "sha1": "bf5b1522f1ad97c1d9a4ff3a15b6b71756348da6", "format": "TIFF"}, {"name": "PTIFF/chnmany_0059.tif", "source": "original", "md5": "44bc8d73e3ad4f183fb123ff23e5211c", "mtime": "1051132754", "size": "14214644", "crc32": "45ad3c81", "sha1": "69d3607e140da60a0ec08396f54e8d6c7c29793e", "format": "TIFF"}, {"name": "PTIFF/chnmany_0060.tif", "source": "original", "md5": "15241d37f1dc4f44e7b4585e02c6cd1d", "mtime": "1051132731", "size": "14037308", "crc32": "3deb433c", "sha1": "02705edce57e0438d93d02ef7b264c3b71c7f720", "format": "TIFF"}, {"name": "PTIFF/chnmany_0061.tif", "source": "original", "md5": "485e2078f38da5d663a5b80842716d18", "mtime": "1051132712", "size": "14494960", "crc32": "9acfeff3", "sha1": "14b4940148b2657866850a452a82d408ecc4fad0", "format": "TIFF"}, {"name": "PTIFF/chnmany_0062.tif", "source": "original", "md5": "4b8ef352c58bdfb5af000c42f8bb0800", "mtime": "1051132642", "size": "13894272", "crc32": "75dcc355", "sha1": "cc0de10e0fed6aa4effe6768234804d9d1ea8f21", "format": "TIFF"}, {"name": "PTIFF/chnmany_0063.tif", "source": "original", "md5": "d72221420a9f45a960490953fcdc8188", "mtime": "1051132621", "size": "14461672", "crc32": "cad29560", "sha1": "e5d3520b5e1fdb4983db3fbc584a1e2a0abc21b6", "format": "TIFF"}, {"name": "PTIFF/chnmany_0064.tif", "source": "original", "md5": "f20a4eddaf33b68b879be32167b0446b", "mtime": "1051132906", "size": "13916216", "crc32": "114efe67", "sha1": "0bec4b9e98a21e5cb96c4b15fc1844a1fd21bb89", "format": "TIFF"}, {"name": "PTIFF/chnmany_0065.tif", "source": "original", "md5": "0d5a97f21b440208d6fa3b87dc8ba3db", "mtime": "1051132564", "size": "14785488", "crc32": "2d38ebb0", "sha1": "f1d220e6f5be708733e8c3c68a30266892091ab4", "format": "TIFF"}, {"name": "PTIFF/chnmany_0066.tif", "source": "original", "md5": "95223cf7abff2ee5338d062fa98ba90d", "mtime": "1051133218", "size": "14245508", "crc32": "ac017995", "sha1": "1b6625cfb9f055b24ee5bc42bf48c24e651402ca", "format": "TIFF"}, {"name": "PTIFF/chnmany_0067.tif", "source": "original", "md5": "4e1a468b91b142e580e13265edc388b3", "mtime": "1051133286", "size": "15649224", "crc32": "9dc6f8ce", "sha1": "48633fb705d9dd469b94e3b852bb3f8feb05318c", "format": "TIFF"}, {"name": "PTIFF/chnmany_0068.tif", "source": "original", "md5": "7db4f4d529bef7d0e8967fda5a404642", "mtime": "1051133277", "size": "15634328", "crc32": "82413e2f", "sha1": "0bba34b70d493f13025541771b5d76841a68345f", "format": "TIFF"}, {"name": "PTIFF/chnmany_0069.tif", "source": "original", "md5": "209f0eaaf2ad5c7fe1b46394513ed4a1", "mtime": "1050102600", "size": "16424036", "crc32": "f36bad6d", "sha1": "b60097d567e25217d68aef5fe63d81753260b306", "format": "TIFF"}, {"name": "PTIFF/chnmany_0070.tif", "source": "original", "md5": "93dce141fc347ce6b02a25a0da2f64ca", "mtime": "1051133266", "size": "14196316", "crc32": "68db7b0f", "sha1": "24dc66d9cfb11ec125c5b6c7aa2228df82614fc6", "format": "TIFF"}, {"name": "PTIFF/chnmany_0071.tif", "source": "original", "md5": "5904c30844e6256aed7b61d34bcd631a", "mtime": "1051133258", "size": "14609040", "crc32": "f930e87e", "sha1": "5ae806b1c21872ff57d7e12472a7792ac1704092", "format": "TIFF"}, {"name": "PTIFF/chnmany_0072.tif", "source": "original", "md5": "b59866edcbbf0934ba757e0798f9cd30", "mtime": "1051133249", "size": "13994264", "crc32": "cc8d94f5", "sha1": "ef33e42a1fd42b376b66370696c4146fc0cb888f", "format": "TIFF"}, {"name": "PTIFF/chnmany_0073.tif", "source": "original", "md5": "38833099f72edcaa07a21ebb540e2a7d", "mtime": "1050103236", "size": "16423868", "crc32": "0e042399", "sha1": "31a9ff23f20e252e2931d603014defeb1271bdbe", "format": "TIFF"}, {"name": "PTIFF/chnmany_0074.tif", "source": "original", "md5": "3fd7e33d6c216f4699a939da7ce84ec1", "mtime": "1051133228", "size": "14992528", "crc32": "06e67e76", "sha1": "50ac08e1c5a467a1aa9b391936a41e7df1d85797", "format": "TIFF"}, {"name": "PTIFF/chnmany_0075.tif", "source": "original", "md5": "9ea8fdeeadad088fcdb0d5cd44c560db", "mtime": "1050103244", "size": "16424368", "crc32": "d73a6f02", "sha1": "8b4229a261ef7fd87ffd7580f5f2f766f69d7e2a", "format": "TIFF"}, {"name": "PTIFF/chnmany_0076.tif", "source": "original", "md5": "23d11016a62fb83b40e468da968d49c0", "mtime": "1051133306", "size": "13926284", "crc32": "4736ab27", "sha1": "350656d28e1c9fa9baa51488b4d449e6c60e24d3", "format": "TIFF"}, {"name": "PTIFF/chnmany_0077.tif", "source": "original", "md5": "46c14418650c73bd4c8eb8f1a1430ce2", "mtime": "1051133639", "size": "15902396", "crc32": "e9fecd5e", "sha1": "088e612340d300459e372f4913ecdc63e9a2e4d6", "format": "TIFF"}, {"name": "PTIFF/chnmany_0078.tif", "source": "original", "md5": "b2953c422c52ba71a5a9c32d2d01b0d2", "mtime": "1051133628", "size": "13773516", "crc32": "130f25cf", "sha1": "dc304b3be1361cc6739b2b0fff29b6c7bcaaad54", "format": "TIFF"}, {"name": "PTIFF/chnmany_0079.tif", "source": "original", "md5": "9328177c4923ce5ff74db32a5132da45", "mtime": "1051133612", "size": "14192700", "crc32": "1ff71baf", "sha1": "701f2e1c315ab78cbd96769dac3a14d77ecd5cd6", "format": "TIFF"}, {"name": "PTIFF/chnmany_0080.tif", "source": "original", "md5": "a783e032f2f94ac5a460a565ce18b208", "mtime": "1051133604", "size": "13991384", "crc32": "7a35c3ad", "sha1": "5275777fda3b697372c09821c3be4eae3c20be73", "format": "TIFF"}, {"name": "PTIFF/chnmany_0081.tif", "source": "original", "md5": "f3e7e69d78ceb35edc493e931458081e", "mtime": "1051133584", "size": "14563372", "crc32": "b80e8167", "sha1": "04519dc9b670aa7ffe003f6152ac967ca0f1482b", "format": "TIFF"}, {"name": "PTIFF/chnmany_0082.tif", "source": "original", "md5": "47109dfad5fcf7f98d57730c9b5eccdb", "mtime": "1051133565", "size": "14165196", "crc32": "f327e047", "sha1": "464f4ab35225f5d8ad6343c79e82a73fc6d344a2", "format": "TIFF"}, {"name": "PTIFF/chnmany_0083.tif", "source": "original", "md5": "26dfa07d271868fe4ba9714e97d58fff", "mtime": "1051133549", "size": "15493940", "crc32": "0a80a4c3", "sha1": "9e5858802a8e58f1a5e20b40f11c423fbda06bf0", "format": "TIFF"}, {"name": "PTIFF/chnmany_0084.tif", "source": "original", "md5": "4b542b78bcb51a69ef5cc06a4590554b", "mtime": "1051133464", "size": "13928240", "crc32": "6c03cc5a", "sha1": "5503882a1e66e41f4080b48e0a04d81205136a58", "format": "TIFF"}, {"name": "PTIFF/chnmany_0085.tif", "source": "original", "md5": "6f3acf58d9fee578ae8ff4c5ed10c027", "mtime": "1051133442", "size": "14895152", "crc32": "2ab51c69", "sha1": "30b8bd42775ff6fa9d229b3be6e6e4afe3a5015f", "format": "TIFF"}, {"name": "PTIFF/chnmany_0086.tif", "source": "original", "md5": "c928186a6b7f162bd6a1cb7c8c418376", "mtime": "1051133434", "size": "14212152", "crc32": "a2973038", "sha1": "623daa87b5aebba104d24db2d1b1d791aceb7c84", "format": "TIFF"}, {"name": "PTIFF/chnmany_0087.tif", "source": "original", "md5": "a11870582dd393fca6a5cf37a4a9d32e", "mtime": "1051133418", "size": "15317808", "crc32": "a9e5940c", "sha1": "1402bdee84d749c32fb5ff36ad83430a8d3661ac", "format": "TIFF"}, {"name": "PTIFF/chnmany_0088.tif", "source": "original", "md5": "be31a21929b5c7ef16bd367ea8e9858d", "mtime": "1051134241", "size": "14210040", "crc32": "67261968", "sha1": "60932640545e74ff2c9ba0e20962552f9439cb7d", "format": "TIFF"}, {"name": "PTIFF/chnmany_0089.tif", "source": "original", "md5": "2174c2f70fa9b1769c90bb27247e2be3", "mtime": "1051134546", "size": "15352468", "crc32": "52e109b6", "sha1": "12edcfa5cb9a849c8c7c75e5204e673fecae7535", "format": "TIFF"}, {"name": "PTIFF/chnmany_0090.tif", "source": "original", "md5": "4da7c685c2d0c92dd19e52b730c74270", "mtime": "1051134403", "size": "14232484", "crc32": "d0fd4407", "sha1": "4fe2c187d217eef03d9dfac9dd302adba7832090", "format": "TIFF"}, {"name": "PTIFF/chnmany_0091.tif", "source": "original", "md5": "ef52a371ce241ae9b8b1ec08b1a7b56d", "mtime": "1051134385", "size": "15015792", "crc32": "1143c4f1", "sha1": "cc3ef3ee9c5ffd210d84fe359cd942de51d55876", "format": "TIFF"}, {"name": "PTIFF/chnmany_0092.tif", "source": "original", "md5": "bfc9e9d4591592170f3dd1ef357406a7", "mtime": "1051134362", "size": "14540584", "crc32": "fff40fa2", "sha1": "4e55b36c59412c0c287e45c3784f7ce3fb51f83b", "format": "TIFF"}, {"name": "PTIFF/chnmany_0093.tif", "source": "original", "md5": "bdd15a700235916899bce7f39e93419f", "mtime": "1051134341", "size": "14861368", "crc32": "1459a818", "sha1": "d7a95d7f0572d9ad50117aabbc7c63acb60cd339", "format": "TIFF"}, {"name": "PTIFF/chnmany_0094.tif", "source": "original", "md5": "fd52e31931dc184cf1c2e0278247d878", "mtime": "1051134333", "size": "14504664", "crc32": "2bcd7427", "sha1": "897bffb14ed87e5f16d8b5a1874d22b1cb04e436", "format": "TIFF"}, {"name": "PTIFF/chnmany_0095.tif", "source": "original", "md5": "7e2cf810d6e398b60bf786046d14c50b", "mtime": "1051134322", "size": "15315268", "crc32": "c9f60ce8", "sha1": "73095a81aa5697b1d41f2cd6408939cae43d9646", "format": "TIFF"}, {"name": "PTIFF/chnmany_0096.tif", "source": "original", "md5": "1228a5fbeac0402ee092e4cd22aa3ff4", "mtime": "1051134258", "size": "14427280", "crc32": "62ea5fd5", "sha1": "b3b35a473c0b0c16a4837b089be8b737e13b9977", "format": "TIFF"}, {"name": "PTIFF/chnmany_0097.tif", "source": "original", "md5": "a8d8d89e2b08d46c041a30ba5bf1d282", "mtime": "1051134250", "size": "14779596", "crc32": "5889c9d4", "sha1": "16493740363d8f12a55ecf207fe05e35feb0819a", "format": "TIFF"}, {"name": "PTIFF/chnmany_0098.tif", "source": "original", "md5": "28cf94b3eda5136cd1cd688c5fd25d5a", "mtime": "1051134564", "size": "14393420", "crc32": "9116569d", "sha1": "834fdf6a0eb76f17e3911767ab42e615e00ec0a5", "format": "TIFF"}, {"name": "PTIFF/chnmany_0099.tif", "source": "original", "md5": "a7e22580fe9298e9c4a02d39780a6eea", "mtime": "1051134604", "size": "15607528", "crc32": "3567b251", "sha1": "355e7a277b407966eceb359e3d122931df93b25e", "format": "TIFF"}, {"name": "PTIFF/chnmany_0100.tif", "source": "original", "md5": "408ffd38457f67f02759e5fbe584c1e1", "mtime": "1051134597", "size": "15090164", "crc32": "8bad09c5", "sha1": "4d6cfb73d3f18aeb73945578f75c0b32fe1c8780", "format": "TIFF"}, {"name": "PTIFF/chnmany_0101.tif", "source": "original", "md5": "3dd38a86e3c472653f19d9bd847fb7b6", "mtime": "1051134590", "size": "15889944", "crc32": "8408acd7", "sha1": "a5fc4aa7fc70d838df4e7fa8873bf0c768e8a918", "format": "TIFF"}, {"name": "PTIFF/chnmany_0102.tif", "source": "original", "md5": "bd02a5a7fae90202bc3ae6697988550c", "mtime": "1050104275", "size": "15566832", "crc32": "df0b0c84", "sha1": "885e625b46ddcef22b56162065eee2f4a778e6ee", "format": "TIFF"}, {"name": "PTIFF/chnmany_0103.tif", "source": "original", "md5": "9d4a19fff4157c15a015c4254734df86", "mtime": "1050104277", "size": "16420672", "crc32": "f123c468", "sha1": "2270d0510f776f6574185485dc62c8e413486098", "format": "TIFF"}, {"name": "PTIFF/chnmany_0104.tif", "source": "original", "md5": "a5f1f61c87148722377672f0bf729d65", "mtime": "1050104278", "size": "16724456", "crc32": "c234a5fa", "sha1": "15ae56ff8dc51b458782af76f54d1f1ea74f1f36", "format": "TIFF"}, {"name": "__ia_thumb.jpg", "source": "original", "mtime": "1530594359", "size": "16416", "md5": "b496ff40148b72fd2790180cab5fdeaf", "crc32": "7b85c76a", "sha1": "ff2f429d0003220fafd05b8db33b759e743665e1", "format": "JPEG Thumb", "rotation": "0"}, {"name": "chnmany.djvu", "source": "derivative", "format": "DjVu", "original": "chnmany_djvu.xml", "md5": "7f442ce6fec974e3afcf5ee97e4443a3", "mtime": "1057857818", "size": "3838889", "crc32": "21f54503", "sha1": "96cdb814176c1dd36d8e62566caa4ddae4f0b77a"}, {"name": "chnmany.tif", "source": "original", "md5": "d6fcb0a6ad99324e736b8066e238f290", "mtime": "1057007063", "size": "1552596088", "crc32": "df1c5588", "sha1": "64e617e8bcaec10d0afd7d173dab8c422d734e3d", "format": "TIFF"}, {"name": "chnmany_archive.torrent", "source": "metadata", "btih": "f59d40aab5d430d59755078e448f1339a3edee02", "mtime": "1530594360", "size": "86937", "md5": "9537f100170e4b4bee685926860018d8", "crc32": "b56a8f60", "sha1": "10f7ffbcd62fd9226a18b19c79e2a803d4a521a4", "format": "Archive BitTorrent"}, {"name": "chnmany_cover.sxw", "source": "original", "md5": "a7e24132a776fff804f8b413ac99cc75", "mtime": "1057880704", "size": "5385244", "crc32": "ef03dd71", "sha1": "c8b83eff6cc04ef61424e0f41b18f10b29ebc21f", "format": "Book Cover"}, {"name": "chnmany_files.xml", "source": "metadata", "format": "Metadata", "md5": "0febf384430d18f617960da8f76b4d3c", "summation": "md5"}, {"name": "chnmany_meta.xml", "source": "metadata", "format": "Metadata", "mtime": "1706037403", "size": "2004", "md5": "8014f6f34a64be849117a66e2714f46e", "crc32": "e6273039", "sha1": "dbe71775b6375e1244703692319bf9e5298d9e9b"}, {"name": "chnmany_original.xml", "source": "original", "md5": "fa4c2f85c6ee6fc1bcd3c9813ed9415f", "mtime": "1057875821", "size": "2437", "crc32": "76b7b7bb", "sha1": "80438205c1357633fec8da2f337e00fdf49ade3a", "format": "Metadata"}], "files_count": 217, "item_last_updated": 1706037403, "item_size": 3406599405, "metadata": {"creator": "S K Chan, W L Yam, P Y Lee", "description": "Story 1: Shiu Shiu (few) lived in a small cloud and Dao Dao (many) lived in a large cloud. The greedy Dao Dao intended to forcibly occupy Shiu Shiu's cloud. Would his plan be successful? Story 2: Could the little elephant swim in the river and fly in the sky? One time, the little elephant played somewhere and went too far away from its mother. How would it return to its mother? Story 3: There were two cats in a forest and they were good friends. One of the cats loved beauty very much. She only attended to the foppery all day and ignored her friend. Finally, the cat got the precept and the story was about the way her friend helped her from danger?\n<br /><br /><br /><table><tr><td><img src=\"http://www.archive.org/images/icdllogo.jpg\" alt=\"icdllogo.jpg\" /></td>\n<td>You can also  <a href=\"http://www.icdlbooks.org:8080/servlet/BookPreview?bookid=chnmany_00120002&summary=true&route=text\" rel=\"nofollow\">read a copy of 'Many And Few'</a> by going to the <a href=\"http://www.icdlbooks.org\" rel=\"nofollow\">International Children's Digital Library</a>, a joint project of the Internet Archive and University Of Maryland.</td>\n</tr></table>", "mediatype": "texts", "scanningcentre": "Hong Kong Public Libraries", "numeric_id": "66170", "date": "1996", "identifier": "chnmany", "type": "Text", "language": "chi", "title": "Many And Few", "collectionid": "chnmany", "collection": "iacl", "public_date": "2003-07-10 17:41:39", "addeddate": "2003-07-10 17:41:39", "updatedate": "2003-11-13 18:39:35", "filesxml": "Thu Dec 14 21:58:26 UTC 2006", "publicdate": "2013-10-23 21:43:04", "backup_location": "ia905708_28"}, "server": "ia801305.us.archive.org", "servers_unavailable": true, "uniq": 1191401137, "workable_servers": ["ia801305.us.archive.org"]}
