{"alternate_locations": {"servers": [{"server": "dn790008.ca.archive.org", "dir": "/0/items/catechismofhisto00daviiala"}], "workable": [{"server": "dn790008.ca.archive.org", "dir": "/0/items/catechismofhisto00daviiala"}]}, "created": 1739344123, "d1": "ia601607.us.archive.org", "d2": "ia801607.us.archive.org", "dir": "/27/items/catechismofhisto00daviiala", "files": [{"name": "__ia_thumb.jpg", "source": "original", "mtime": "1692813626", "size": "19320", "md5": "602a0830685ef755a4e58229e9d0d46f", "crc32": "4814c19a", "sha1": "b98cfd0033ad79a624f1470c7825a28a6dd43904", "format": "Item Tile", "rotation": "0"}, {"name": "_cloth_detection.log", "source": "derivative", "cloth_cover_detection_module_version": "1.2", "format": "Cloth Cover Detection Log", "original": "scandata.zip", "mtime": "1699176009", "size": "715", "md5": "d4c60bda7285487c8e41d817b29ccbca", "crc32": "383b69cb", "sha1": "18187a593b0900ca9bc93f9ffc465d827f629d5d"}, {"name": "catechismofhisto00daviiala.djvu", "source": "derivative", "format": "DjVu", "original": "catechismofhisto00daviiala_djvu.xml", "md5": "8996ab22f383b467cb311925e0edcd16", "mtime": "1163793508", "size": "3386470", "crc32": "e08c479b", "sha1": "2c1b41561e863519b54d9323ed08269f63b86592"}, {"name": "catechismofhisto00daviiala.gif", "source": "derivative", "format": "Animated GIF", "original": "catechismofhisto00daviiala_jp2.zip", "md5": "0d5642cb1bac2736cbebe91c028420a0", "mtime": "1163791516", "size": "412533", "crc32": "70a6334c", "sha1": "787235102fd742537c2bb1f605a66602aa060ba9"}, {"name": "catechismofhisto00daviiala.pdf", "source": "derivative", "format": "Text PDF", "original": "catechismofhisto00daviiala_page_numbers.json", "mtime": "1699175834", "size": "4125838", "md5": "756c331e70e4ed2c7d96b9abe2378ede", "crc32": "8ffed121", "sha1": "9c9811a7c180e0d137d3ff418c81dbe39127a494"}, {"name": "catechismofhisto00daviiala_abbyy.gz", "source": "derivative", "format": "Abbyy GZ", "original": "catechismofhisto00daviiala_jp2.zip", "md5": "9b8da1911a5ef896844092f2d66606ae", "mtime": "1163793226", "size": "1825467", "crc32": "3a8091f6", "sha1": "ab16556143a2d9398655ff4f3ffe9885f868ce57"}, {"name": "catechismofhisto00daviiala_archive.torrent", "source": "metadata", "btih": "cc0f33e8590c6f1359c0fba4604499915268bb1d", "mtime": "1699176814", "size": "11102", "md5": "e7c9f1f2d261a1b2fe20879d5471efd5", "crc32": "018f14e8", "sha1": "6bbfb7f690999ff06cd8a605e0c2ea107b4096c8", "format": "Archive BitTorrent"}, {"name": "catechismofhisto00daviiala_bw.pdf", "source": "derivative", "format": "Grayscale PDF", "original": "catechismofhisto00daviiala_page_numbers.json", "mtime": "1699175835", "size": "3432733", "md5": "ed95c8b61ceecae3bd7847722613573b", "crc32": "03cfd545", "sha1": "286540e7f004f9da1ebe6079406c3b91aad2bb59"}, {"name": "catechismofhisto00daviiala_chocr.html.gz", "source": "derivative", "ocr_module_version": "0.0.21", "ocr_converted": "abbyy-to-hocr 1.1.37", "format": "chOCR", "original": "catechismofhisto00daviiala_abbyy.gz", "mtime": "1699175161", "size": "1473512", "md5": "bf4d2a3c458178de35d6df6696307cc6", "crc32": "a4349419", "sha1": "d984bf887f57b7cdbbab229c260aa49774c189b6"}, {"name": "catechismofhisto00daviiala_dc.xml", "source": "original", "md5": "e6bcc859656b600413ca46dc4f97d7c8", "format": "Dublin Core", "mtime": "1648264438", "size": "1051", "crc32": "0e302693", "sha1": "d10661474cb85e3de3e850edbf499cf6f455696c"}, {"name": "catechismofhisto00daviiala_djvu.txt", "source": "derivative", "format": "DjVuTXT", "original": "catechismofhisto00daviiala_djvu.xml", "mtime": "1699175781", "size": "136914", "md5": "5f36b32446f870aedbffa302540b3cce", "crc32": "4db9f641", "sha1": "3cc057a5ee4cbbc089525a2df88bf37fa52df889"}, {"name": "catechismofhisto00daviiala_djvu.xml", "source": "derivative", "format": "Djvu XML", "original": "catechismofhisto00daviiala_hocr.html", "mtime": "1699175400", "size": "1608444", "md5": "b22297e6adda54e313c0094b6656744c", "crc32": "747a2e60", "sha1": "158b9d446f05a2dab683bad524014a12807ceab9"}, {"name": "catechismofhisto00daviiala_files.xml", "source": "original", "md5": "3009667674c8b577d59b3b926e6c8519", "format": "Metadata", "summation": "md5"}, {"name": "catechismofhisto00daviiala_hocr.html", "source": "derivative", "hocr_char_to_word_module_version": "1.2.0", "hocr_char_to_word_hocr_version": "1.1.45", "ocr_module_version": "0.0.21", "ocr_converted": "abbyy-to-hocr 1.1.37", "format": "hOCR", "original": "catechismofhisto00daviiala_chocr.html.gz", "mtime": "1699175331", "size": "3051634", "md5": "1d7e8eac259030209fa7612dabc5fbf8", "crc32": "27aa8d1e", "sha1": "aa1b3e7cacaab8d27cc53a23cb38312f3e8b86d1"}, {"name": "catechismofhisto00daviiala_hocr_pageindex.json.gz", "source": "derivative", "hocr_pageindex_module_version": "1.0.0", "hocr_pageindex_hocr_version": "1.1.15", "format": "OCR Page Index", "original": "catechismofhisto00daviiala_hocr.html", "mtime": "1699175457", "size": "987", "md5": "42fecc18c0657f40b27ce7405bcd337d", "crc32": "d6a1f6a5", "sha1": "1d843f319faa3980792f98477207ea8f9f1b65c2"}, {"name": "catechismofhisto00daviiala_hocr_searchtext.txt.gz", "source": "derivative", "hocr_fts_text_module_version": "1.1.0", "hocr_fts_text_hocr_version": "1.1.15", "word_conf_0_10": "627", "word_conf_11_20": "1040", "word_conf_21_30": "18378", "word_conf_31_40": "0", "word_conf_41_50": "0", "word_conf_51_60": "0", "word_conf_61_70": "0", "word_conf_71_80": "0", "word_conf_81_90": "0", "word_conf_91_100": "0", "format": "OCR Search Text", "original": "catechismofhisto00daviiala_hocr.html", "mtime": "1699175573", "size": "45982", "md5": "98f3cc51f164f658c432735512603a89", "crc32": "5c3f2af2", "sha1": "31fd95fdf871c10803c266d6a16523ca17e61467"}, {"name": "catechismofhisto00daviiala_jp2.zip", "source": "derivative", "format": "Single Page Processed JP2 ZIP", "original": "catechismofhisto00daviiala_raw_jp2.zip", "md5": "162366192d3bc0509ebb4ae7c5f6cce5", "mtime": "1163791483", "size": "31666533", "crc32": "7077820c", "sha1": "1a662a1b91e7249bef2fe0349e418396847d0b9c", "filecount": "86"}, {"name": "catechismofhisto00daviiala_jpg.zip", "source": "derivative", "format": "Single Page Processed JPEG ZIP", "original": "catechismofhisto00daviiala_jp2.zip", "md5": "42b06d6ec88e9a16752f1092c76c0032", "mtime": "1163791483", "size": "46537715", "crc32": "a2a5a60c", "sha1": "ab823c5f51f54cccd67ac43c0235968eb989d03d", "filecount": "86"}, {"name": "catechismofhisto00daviiala_marc.xml", "source": "original", "md5": "e720f186094ba628015d9897702a3387", "format": "MARC", "mtime": "1163701716", "size": "3268", "crc32": "dfb9df77", "sha1": "a01f0ce9bfa9d5f23456cc81ddee8b23d5d2e15d"}, {"name": "catechismofhisto00daviiala_meta.mrc", "source": "original", "md5": "6e5c5d630faa037b4b28bcb7b81e2fed", "format": "MARC Binary", "mtime": "1163701716", "size": "1173", "crc32": "392b80ea", "sha1": "e265d157161999ec8f5d4fe8bdf9b89f56d666b2"}, {"name": "catechismofhisto00daviiala_meta.sqlite", "source": "original", "mtime": "1467975492", "size": "6144", "format": "Metadata", "md5": "5b8de3d933cf772244c907a05f3ddd3e", "crc32": "806980f2", "sha1": "bb5d3a45fc6462e19c941a854588a3df84e1e8eb"}, {"name": "catechismofhisto00daviiala_meta.xml", "source": "original", "format": "Metadata", "mtime": "1699175917", "size": "2988", "md5": "c628873c5f23e5366ba37ee5dc74f722", "crc32": "4c6562e0", "sha1": "9a4862f18eabc91112f69baeda00997d8405b7a9"}, {"name": "catechismofhisto00daviiala_metasource.xml", "source": "original", "md5": "78926a92a92f53b9d16c0fe869d9f751", "format": "MARC Source", "mtime": "1163701716", "size": "392", "crc32": "5a01163b", "sha1": "43890159e30aba49d960e21d875913fb5e8a06cf"}, {"name": "catechismofhisto00daviiala_page_numbers.json", "source": "derivative", "hocr_pagenumber_module_version": "1.0.3", "hocr_pagenumber_hocr_version": "1.1.54", "hocr_pagenumber_confidence": "100", "format": "Page Numbers JSON", "original": "catechismofhisto00daviiala_hocr.html", "mtime": "1699175758", "size": "14016", "md5": "7d2a3dcaa505fb517aaa6b13c46c190b", "crc32": "32055ab3", "sha1": "5172443724f46cc1d4f2b3757a115db4e4b0d6f9"}, {"name": "catechismofhisto00daviiala_raw_jp2.zip", "source": "original", "format": "Single Page Raw JP2 ZIP", "md5": "83fe22b508ce095eb0e42cfdbd29453d", "mtime": "1163791481", "size": "88580265", "crc32": "755502f6", "sha1": "5aeb603dae3ee973bd95e9849de3bcd882e598b2", "filecount": "86"}, {"name": "scandata.zip", "source": "original", "format": "Scribe Scandata ZIP", "md5": "f52f455c9f536703ec6641f45429b383", "mtime": "1699176002", "size": "47902010", "crc32": "0b805683", "sha1": "2bc7b6a0b5facf5dd8884d93ab795c2caab223bd", "filecount": "11"}], "files_count": 26, "item_last_updated": 1699176814, "item_size": 234247206, "metadata": {"title": "A catechism of the history of America : in two parts", "subject": ["America -- History Juvenile literature", "America -- Discovery and exploration Juvenile literature", "United States -- History Juvenile literature"], "description": "Printed tan stiff wrappers", "publisher": "London : Printed by Davidson, Old Boswell Court : for Pinnock and Maunder, Mentorian Press, 267, (St. Clement's Church Yard), Strand", "date": "1819", "language": "eng", "copyright-evidence-operator": "alyson-wieczorek", "possible-copyright-status": "NOT_IN_COPYRIGHT", "copyright-region": "US", "copyright-evidence": "Evidence reported by alyson-wieczorek for item catechismofhisto00daviiala on November 16, 2006: no visible notice of copyright; stated date is 1819.", "copyright-evidence-date": "20061116182812", "sponsor": "msn", "contributor": "University of California Libraries", "scanningcenter": "iala", "mediatype": "texts", "call_number": "srlf_ucla:LAGE-967764", "collection-library": "ucla_spec", "identifier-bib": "LAGE-967764", "identifier-access": "http://www.archive.org/details/catechismofhisto00daviiala", "updatedate": "2006-11-16 18:28:36", "updater": "alyson-wieczorek", "identifier": "catechismofhisto00daviiala", "uploader": "scanner-alyson-wieczorek@archive.org", "addeddate": "2006-11-16 18:28:38", "publicdate": "2006-11-16 10:28:59", "imagecount": "86", "ppi": "600", "lcamid": "1020707125", "rcamid": "1020707296", "camera": "5D", "operator": "scanner-kelly-critch@archive.org", "scanner": "iala5", "scandate": "20061117182622", "identifier-ark": "ark:/13960/t7fq9r81k", "curation": "[curator]marcus@archive.org[/curator][date]20070112010928[/date][state]approved[/state]", "sponsordate": "20080430", "filesxml": ["Wed Mar 17 6:11:53 UTC 2010", "Wed Dec 23 17:14:27 UTC 2020"], "collection": ["cdl", "yrlsc", "iacl", "americana"], "foldoutcount": "0", "repub_state": "4", "backup_location": "ia903600_25", "openlibrary_edition": "OL7239643M", "openlibrary_work": "OL16736509W", "external-identifier": "urn:oclc:record:1041774368", "oclc-id": "8166196", "ocr_module_version": "0.0.21", "ocr_converted": "abbyy-to-hocr 1.1.37", "page_number_confidence": "100", "page_number_module_version": "1.0.3"}, "page_numbers": {"identifier": "catechismofhisto00daviiala", "format-version": "2", "archive-hocr-tools-version": "1.1.54", "confidence": 100, "pages": [{"leafNum": 1, "confidence": null, "pageNumber": "", "pageProb": null, "wordConf": null}, {"leafNum": 2, "confidence": null, "pageNumber": "", "pageProb": null, "wordConf": null}, {"leafNum": 3, "confidence": null, "pageNumber": "", "pageProb": null, "wordConf": null}, {"leafNum": 4, "confidence": null, "pageNumber": "", "pageProb": null, "wordConf": null}, {"leafNum": 5, "confidence": null, "pageNumber": "", "pageProb": null, "wordConf": null}, {"leafNum": 6, "confidence": null, "pageNumber": "", "pageProb": null, "wordConf": null}, {"leafNum": 7, "confidence": null, "pageNumber": "", "pageProb": null, "wordConf": null}, {"leafNum": 8, "confidence": null, "pageNumber": "", "pageProb": null, "wordConf": null}, {"leafNum": 9, "confidence": 100, "pageNumber": "5", "pageProb": 94, "wordConf": 26}, {"leafNum": 10, "confidence": null, "pageNumber": "6", "pageProb": null, "wordConf": null}, {"leafNum": 11, "confidence": null, "pageNumber": "7", "pageProb": null, "wordConf": null}, {"leafNum": 12, "confidence": null, "pageNumber": "8", "pageProb": null, "wordConf": null}, {"leafNum": 13, "confidence": 100, "pageNumber": "9", "pageProb": 93, "wordConf": 28}, {"leafNum": 14, "confidence": null, "pageNumber": "10", "pageProb": null, "wordConf": null}, {"leafNum": 15, "confidence": 100, "pageNumber": "11", "pageProb": 93, "wordConf": 29}, {"leafNum": 16, "confidence": null, "pageNumber": "12", "pageProb": null, "wordConf": null}, {"leafNum": 17, "confidence": 100, "pageNumber": "13", "pageProb": 94, "wordConf": 30}, {"leafNum": 18, "confidence": null, "pageNumber": "14", "pageProb": null, "wordConf": null}, {"leafNum": 19, "confidence": 100, "pageNumber": "15", "pageProb": 93, "wordConf": 27}, {"leafNum": 20, "confidence": null, "pageNumber": "16", "pageProb": null, "wordConf": null}, {"leafNum": 21, "confidence": 100, "pageNumber": "17", "pageProb": 93, "wordConf": 30}, {"leafNum": 22, "confidence": null, "pageNumber": "18", "pageProb": null, "wordConf": null}, {"leafNum": 23, "confidence": 100, "pageNumber": "19", "pageProb": 94, "wordConf": 26}, {"leafNum": 24, "confidence": null, "pageNumber": "20", "pageProb": null, "wordConf": null}, {"leafNum": 25, "confidence": 100, "pageNumber": "21", "pageProb": 94, "wordConf": 23}, {"leafNum": 26, "confidence": null, "pageNumber": "22", "pageProb": null, "wordConf": null}, {"leafNum": 27, "confidence": 100, "pageNumber": "23", "pageProb": 93, "wordConf": 21}, {"leafNum": 28, "confidence": null, "pageNumber": "24", "pageProb": null, "wordConf": null}, {"leafNum": 29, "confidence": null, "pageNumber": "25", "pageProb": null, "wordConf": null}, {"leafNum": 30, "confidence": null, "pageNumber": "26", "pageProb": null, "wordConf": null}, {"leafNum": 31, "confidence": 100, "pageNumber": "27", "pageProb": 92, "wordConf": 27}, {"leafNum": 32, "confidence": null, "pageNumber": "28", "pageProb": null, "wordConf": null}, {"leafNum": 33, "confidence": 100, "pageNumber": "29", "pageProb": 94, "wordConf": 4}, {"leafNum": 34, "confidence": null, "pageNumber": "30", "pageProb": null, "wordConf": null}, {"leafNum": 35, "confidence": null, "pageNumber": "31", "pageProb": null, "wordConf": null}, {"leafNum": 36, "confidence": null, "pageNumber": "32", "pageProb": null, "wordConf": null}, {"leafNum": 37, "confidence": 100, "pageNumber": "33", "pageProb": 93, "wordConf": 28}, {"leafNum": 38, "confidence": null, "pageNumber": "34", "pageProb": null, "wordConf": null}, {"leafNum": 39, "confidence": null, "pageNumber": "35", "pageProb": null, "wordConf": null}, {"leafNum": 40, "confidence": null, "pageNumber": "36", "pageProb": null, "wordConf": null}, {"leafNum": 41, "confidence": 100, "pageNumber": "37", "pageProb": 93, "wordConf": 29}, {"leafNum": 42, "confidence": null, "pageNumber": "38", "pageProb": null, "wordConf": null}, {"leafNum": 43, "confidence": 100, "pageNumber": "39", "pageProb": 93, "wordConf": 27}, {"leafNum": 44, "confidence": null, "pageNumber": "40", "pageProb": null, "wordConf": null}, {"leafNum": 45, "confidence": 100, "pageNumber": "41", "pageProb": 93, "wordConf": 30}, {"leafNum": 46, "confidence": null, "pageNumber": "42", "pageProb": null, "wordConf": null}, {"leafNum": 47, "confidence": 100, "pageNumber": "43", "pageProb": 93, "wordConf": 29}, {"leafNum": 48, "confidence": null, "pageNumber": "44", "pageProb": null, "wordConf": null}, {"leafNum": 49, "confidence": 100, "pageNumber": "45", "pageProb": 94, "wordConf": 29}, {"leafNum": 50, "confidence": null, "pageNumber": "46", "pageProb": null, "wordConf": null}, {"leafNum": 51, "confidence": 100, "pageNumber": "47", "pageProb": 92, "wordConf": 29}, {"leafNum": 52, "confidence": null, "pageNumber": "48", "pageProb": null, "wordConf": null}, {"leafNum": 53, "confidence": 100, "pageNumber": "49", "pageProb": 93, "wordConf": 28}, {"leafNum": 54, "confidence": null, "pageNumber": "50", "pageProb": null, "wordConf": null}, {"leafNum": 55, "confidence": null, "pageNumber": "51", "pageProb": null, "wordConf": null}, {"leafNum": 56, "confidence": null, "pageNumber": "52", "pageProb": null, "wordConf": null}, {"leafNum": 57, "confidence": null, "pageNumber": "53", "pageProb": null, "wordConf": null}, {"leafNum": 58, "confidence": null, "pageNumber": "54", "pageProb": null, "wordConf": null}, {"leafNum": 59, "confidence": null, "pageNumber": "55", "pageProb": null, "wordConf": null}, {"leafNum": 60, "confidence": null, "pageNumber": "56", "pageProb": null, "wordConf": null}, {"leafNum": 61, "confidence": 100, "pageNumber": "57", "pageProb": 93, "wordConf": 4}, {"leafNum": 62, "confidence": null, "pageNumber": "58", "pageProb": null, "wordConf": null}, {"leafNum": 63, "confidence": null, "pageNumber": "59", "pageProb": null, "wordConf": null}, {"leafNum": 64, "confidence": null, "pageNumber": "60", "pageProb": null, "wordConf": null}, {"leafNum": 65, "confidence": null, "pageNumber": "61", "pageProb": null, "wordConf": null}, {"leafNum": 66, "confidence": null, "pageNumber": "62", "pageProb": null, "wordConf": null}, {"leafNum": 67, "confidence": 100, "pageNumber": "63", "pageProb": 94, "wordConf": 28}, {"leafNum": 68, "confidence": null, "pageNumber": "64", "pageProb": null, "wordConf": null}, {"leafNum": 69, "confidence": 100, "pageNumber": "65", "pageProb": 93, "wordConf": 27}, {"leafNum": 70, "confidence": null, "pageNumber": "66", "pageProb": null, "wordConf": null}, {"leafNum": 71, "confidence": 100, "pageNumber": "67", "pageProb": 94, "wordConf": 29}, {"leafNum": 72, "confidence": null, "pageNumber": "68", "pageProb": null, "wordConf": null}, {"leafNum": 73, "confidence": 100, "pageNumber": "69", "pageProb": 94, "wordConf": 27}, {"leafNum": 74, "confidence": null, "pageNumber": "70", "pageProb": null, "wordConf": null}, {"leafNum": 75, "confidence": 100, "pageNumber": "71", "pageProb": 94, "wordConf": 28}, {"leafNum": 76, "confidence": null, "pageNumber": "", "pageProb": null, "wordConf": null}, {"leafNum": 77, "confidence": null, "pageNumber": "", "pageProb": null, "wordConf": null}, {"leafNum": 78, "confidence": null, "pageNumber": "", "pageProb": null, "wordConf": null}, {"leafNum": 79, "confidence": null, "pageNumber": "", "pageProb": null, "wordConf": null}, {"leafNum": 80, "confidence": null, "pageNumber": "", "pageProb": null, "wordConf": null}, {"leafNum": 81, "confidence": null, "pageNumber": "", "pageProb": null, "wordConf": null}, {"leafNum": 82, "confidence": null, "pageNumber": "", "pageProb": null, "wordConf": null}]}, "server": "ia601607.us.archive.org", "uniq": 1759685756, "workable_servers": ["ia601607.us.archive.org", "ia801607.us.archive.org"]}
