{"created": 1739351337, "d1": "ia600907.us.archive.org", "d2": "ia800907.us.archive.org", "dir": "/27/items/parentsassistant05edgeiala", "files": [{"name": "__ia_thumb.jpg", "source": "original", "mtime": "1692842758", "size": "15444", "md5": "ddbf09208b2f789829c1405f88751d4a", "crc32": "4a4c64af", "sha1": "543763128db1c21362ff4e1b0943de508b49fc28", "format": "Item Tile", "rotation": "0"}, {"name": "parentsassistant05edgeiala.djvu", "source": "derivative", "format": "DjVu", "original": "parentsassistant05edgeiala_djvu.xml", "md5": "ddf9fb2ced30091826357e51bdfe74c8", "mtime": "1172615233", "size": "8633688", "crc32": "18feea19", "sha1": "8b9fc8c8becf7db3d3cec0710787f3e08b2dbbae"}, {"name": "parentsassistant05edgeiala.gif", "source": "derivative", "format": "Animated GIF", "original": "parentsassistant05edgeiala_jp2.zip", "md5": "0fbb9b8091be8ea3aba9dbaf409c72d7", "mtime": "1172613183", "size": "297701", "crc32": "f4c005fe", "sha1": "b5eaf9e59ebcc1d1af2f7d8bd97051db9819013d"}, {"name": "parentsassistant05edgeiala.pdf", "source": "derivative", "format": "Text PDF", "original": "parentsassistant05edgeiala_page_numbers.json", "mtime": "1702221993", "size": "17836874", "md5": "9851640c2f725d9e77e941968b9a3989", "crc32": "178c0031", "sha1": "38f4f1a62faf31ae9602e4625f2a78b9c9675856"}, {"name": "parentsassistant05edgeiala_abbyy.gz", "source": "derivative", "format": "Abbyy GZ", "original": "parentsassistant05edgeiala_jp2.zip", "md5": "51d5e4e920e04445ee3d437c95c24483", "mtime": "1172614569", "size": "3142093", "crc32": "30742f66", "sha1": "9551c830b87f2334e7ac81a6db81bb6ff937162b"}, {"name": "parentsassistant05edgeiala_archive.torrent", "source": "metadata", "btih": "df89c8377d29e5685e4d9ff15d2945b8aab47eff", "mtime": "1702222168", "size": "12450", "md5": "274e448a67d4333953e0878bad2b0a4f", "crc32": "28d8a266", "sha1": "feb868322c488a72cc7410f0ee2728c039fd3154", "format": "Archive BitTorrent"}, {"name": "parentsassistant05edgeiala_bw.pdf", "source": "derivative", "format": "Grayscale PDF", "original": "parentsassistant05edgeiala_page_numbers.json", "mtime": "1702221993", "size": "7169643", "md5": "4ffd3b0d87871594069b0aafd3b26738", "crc32": "6b45b259", "sha1": "805d865b347d83540a6186bf38aa5774fccd0e2f"}, {"name": "parentsassistant05edgeiala_chocr.html.gz", "source": "derivative", "ocr_module_version": "0.0.21", "ocr_converted": "abbyy-to-hocr 1.1.37", "format": "chOCR", "original": "parentsassistant05edgeiala_abbyy.gz", "mtime": "1702221886", "size": "2588354", "md5": "3ee8fafc3c3bae6ad0db0d31cfc2ebaa", "crc32": "ed34a492", "sha1": "bf2e17499c4bc4ea3c5a94b1ce8291ad05a7d6d5"}, {"name": "parentsassistant05edgeiala_dc.xml", "source": "original", "md5": "9d823aa09fc89191eda2fafee3634023", "format": "Dublin Core", "mtime": "1649142120", "size": "1357", "crc32": "ab9f2909", "sha1": "4928ec8ec5c1cadcbe9410a3327476bf1153a821"}, {"name": "parentsassistant05edgeiala_djvu.txt", "source": "derivative", "format": "DjVuTXT", "original": "parentsassistant05edgeiala_djvu.xml", "mtime": "1702221954", "size": "233012", "md5": "4796d7b851457b303186e0b3374e6249", "crc32": "e23a1735", "sha1": "bd5c4212e45a55a8322d3bea1d4d5f255cf52bfe"}, {"name": "parentsassistant05edgeiala_djvu.xml", "source": "derivative", "format": "Djvu XML", "original": "parentsassistant05edgeiala_hocr.html", "mtime": "1702221910", "size": "3030915", "md5": "2c434192c8e84ee1b61d0293ca577c5b", "crc32": "3788e2ca", "sha1": "4cb25d28e279d9249966c42f02c51d4e18bf7b7e"}, {"name": "parentsassistant05edgeiala_files.xml", "source": "original", "md5": "716aecf78fefd939c1db9853cbe78407", "format": "Metadata", "summation": "md5"}, {"name": "parentsassistant05edgeiala_hocr.html", "source": "derivative", "hocr_char_to_word_module_version": "1.2.0", "hocr_char_to_word_hocr_version": "1.1.45", "ocr_module_version": "0.0.21", "ocr_converted": "abbyy-to-hocr 1.1.37", "format": "hOCR", "original": "parentsassistant05edgeiala_chocr.html.gz", "mtime": "1702221901", "size": "5752596", "md5": "3e85c84a6445633fcf0b850ecc6e91b1", "crc32": "04884603", "sha1": "c9c595fa9356e428d8b9be1d7ed26931addd0059"}, {"name": "parentsassistant05edgeiala_hocr_pageindex.json.gz", "source": "derivative", "hocr_pageindex_module_version": "1.0.0", "hocr_pageindex_hocr_version": "1.1.15", "format": "OCR Page Index", "original": "parentsassistant05edgeiala_hocr.html", "mtime": "1702221916", "size": "2842", "md5": "6ba499823780729f6366605011063833", "crc32": "bce7989d", "sha1": "75f3a0c10717d0b453763bb0986a3615cc381927"}, {"name": "parentsassistant05edgeiala_hocr_searchtext.txt.gz", "source": "derivative", "hocr_fts_text_module_version": "1.1.0", "hocr_fts_text_hocr_version": "1.1.15", "word_conf_0_10": "3275", "word_conf_11_20": "4335", "word_conf_21_30": "29996", "word_conf_31_40": "0", "word_conf_41_50": "0", "word_conf_51_60": "0", "word_conf_61_70": "0", "word_conf_71_80": "0", "word_conf_81_90": "0", "word_conf_91_100": "0", "format": "OCR Search Text", "original": "parentsassistant05edgeiala_hocr.html", "mtime": "1702221932", "size": "78134", "md5": "631b0b2de18787dcdc0480493b6bf411", "crc32": "33d27dc5", "sha1": "88b8850c4b76e3b1eb6ee927c30a8e3993694b67"}, {"name": "parentsassistant05edgeiala_jp2.zip", "source": "derivative", "format": "Single Page Processed JP2 ZIP", "original": "parentsassistant05edgeiala_raw_jp2.zip", "md5": "cd70020d5eb9c4dc1123ab60dbe4d070", "mtime": "1172613143", "size": "97508302", "crc32": "8f7a4d7c", "sha1": "fe23bf03f0b9b6107157b10a89fbe6dcc6cf9086", "filecount": "250"}, {"name": "parentsassistant05edgeiala_marc.xml", "source": "original", "md5": "c985631d9a53b056a2dbe1e9d5c5905a", "format": "MARC", "mtime": "1172507578", "size": "4562", "crc32": "f93e6d07", "sha1": "7c333b96f6a4d180c841c0993c69873a5640b822"}, {"name": "parentsassistant05edgeiala_meta.mrc", "source": "original", "md5": "2f2fd06d58eefde1714ff92e26216569", "format": "MARC Binary", "mtime": "1172507578", "size": "2059", "crc32": "35adc42c", "sha1": "363dc04e2e0284f3690b32de6ae99e5760874141"}, {"name": "parentsassistant05edgeiala_meta.xml", "source": "original", "format": "Metadata", "mtime": "1702222163", "size": "3552", "md5": "3091737f7d82c42dec97860c54769106", "crc32": "5eea1dff", "sha1": "7c836cf21a367fdbcabf2c00a43e34c60d536a3b"}, {"name": "parentsassistant05edgeiala_metasource.xml", "source": "original", "md5": "68e1bbf87f8782b880b0e03b0f3aee50", "format": "MARC Source", "mtime": "1172507578", "size": "383", "crc32": "2a5a2356", "sha1": "dd7f42c18bc77fe39050c5bc7053c858efb3414e"}, {"name": "parentsassistant05edgeiala_page_numbers.json", "source": "derivative", "hocr_pagenumber_module_version": "1.0.3", "hocr_pagenumber_hocr_version": "1.1.54", "hocr_pagenumber_confidence": "92", "format": "Page Numbers JSON", "original": "parentsassistant05edgeiala_hocr.html", "mtime": "1702221945", "size": "42092", "md5": "cc5fd7a8f0b373eb8aa3a0544b4f1783", "crc32": "309c3652", "sha1": "6e2dedfb05d25f728f327cf9eefd553057c71fb1"}, {"name": "parentsassistant05edgeiala_raw_jp2.zip", "source": "original", "format": "Single Page Raw JP2 ZIP", "md5": "dedeba68645ac75a3b35305ae60da72b", "mtime": "1172613125", "size": "198316908", "crc32": "a7117df6", "sha1": "e8f18b4b890cb5a30667074b1f20f644654ef25a", "filecount": "250"}, {"name": "scandata.zip", "source": "original", "format": "Scribe Scandata ZIP", "md5": "93e30856ac8a506b612f773b465aba9f", "mtime": "1172604418", "size": "48743458", "crc32": "982b4f20", "sha1": "4239d98507fe2d8798d636ae5b9087e6288c9253", "filecount": "11"}], "files_count": 23, "item_last_updated": 1702222168, "item_size": 393416419, "metadata": {"title": "The parent's assistant, or, Stories for children", "volume": "5", "creator": "Edgeworth, Maria, 1767-1849", "subject": ["Conduct of life", "Children's stories, English"], "description": ["v. 1. Lazy Lawrence, Tarlton, False key--v. 2. The birthday present, Simple Susan--v. 3. The bracelets, The little merchants--v. 4. Old Poz the mimic, Mademoiselle Panache--v. 5. The basket-woman, The white pigeon, The orphans, Waste not want not, Forgive and forget--v. 6. The barring out, Eton Montem", "Special Collections copy 1 = Green morocco over boards blocked in blind and gold, gilt edges. Volume 1 lacks general title page and preface. Volume 3 has an extra engraved \"frontispiece\" bound in preceding p.[77]. The title page in each volume bears the inscription: Fanny Edgeworth with her sister Maria's love", "Special Collections copy 2 = Half brown calf and marbled paper over boards. Ex libris May & George Shiers. Volume 1 includes general title page and preface bound in front of text"], "publisher": "London (No. 72, St. Paul's Church-yard) : J. Johnson", "date": "1800", "language": "eng", "copyright-evidence-operator": "alyson-wieczorek", "possible-copyright-status": "NOT_IN_COPYRIGHT", "copyright-region": "US", "copyright-evidence": "Evidence reported by alyson-wieczorek for item parentsassistant05edgeiala on February 26, 2007: no visible notice of copyright; stated date is 1800.", "copyright-evidence-date": "20070226163218", "sponsor": "msn", "contributor": "University of California Libraries", "scanningcenter": "iala", "mediatype": "texts", "call_number": "srlf_ucla:LAGE-1263583", "collection-library": "ucla_spec", "identifier-bib": "LAGE-1263583", "identifier-access": "http://www.archive.org/details/parentsassistant05edgeiala", "updatedate": "2007-02-26 16:32:57", "updater": "alyson-wieczorek", "identifier": "parentsassistant05edgeiala", "uploader": "scanner-alyson-wieczorek@archive.org", "addeddate": "2007-02-26 16:33:00", "publicdate": "2007-02-26 08:33:02", "imagecount": "250", "ppi": "500", "lcamid": "1020705142", "rcamid": "1020707124", "camera": "5D", "operator": "scanner-martha-sanchez@archive.org", "scanner": "iala5", "scandate": "20070227191527", "identifier-ark": "ark:/13960/t9w08zb4c", "curation": "[curator]marcus@archive.org[/curator][date]20070309214307[/date][state]approved[/state]", "sponsordate": "20080430", "filesxml": ["Thu Mar 18 7:26:17 UTC 2010", "Fri Dec 25 16:49:07 UTC 2020"], "collection": ["cdl", "yrlsc", "iacl", "americana"], "backup_location": "ia903600_30", "external-identifier": "urn:oclc:record:1050262620", "oclc-id": "23594636", "foldoutcount": "0", "ocr_module_version": "0.0.21", "ocr_converted": "abbyy-to-hocr 1.1.37", "page_number_confidence": "92", "page_number_module_version": "1.0.3"}, "page_numbers": {"identifier": "parentsassistant05edgeiala", "format-version": "2", "archive-hocr-tools-version": "1.1.54", "confidence": 92, "pages": [{"leafNum": 1, "confidence": null, "pageNumber": "", "pageProb": null, "wordConf": null}, {"leafNum": 2, "confidence": null, "pageNumber": "", "pageProb": null, "wordConf": null}, {"leafNum": 3, "confidence": null, "pageNumber": "", "pageProb": null, "wordConf": null}, {"leafNum": 4, "confidence": null, "pageNumber": "", "pageProb": null, "wordConf": null}, {"leafNum": 5, "confidence": null, "pageNumber": "", "pageProb": null, "wordConf": null}, {"leafNum": 6, "confidence": null, "pageNumber": "", "pageProb": null, "wordConf": null}, {"leafNum": 7, "confidence": null, "pageNumber": "", "pageProb": null, "wordConf": null}, {"leafNum": 8, "confidence": null, "pageNumber": "", "pageProb": null, "wordConf": null}, {"leafNum": 9, "confidence": null, "pageNumber": "", "pageProb": null, "wordConf": null}, {"leafNum": 10, "confidence": null, "pageNumber": "", "pageProb": null, "wordConf": null}, {"leafNum": 11, "confidence": null, "pageNumber": "", "pageProb": null, "wordConf": null}, {"leafNum": 12, "confidence": null, "pageNumber": "", "pageProb": null, "wordConf": null}, {"leafNum": 13, "confidence": null, "pageNumber": "", "pageProb": null, "wordConf": null}, {"leafNum": 14, "confidence": null, "pageNumber": "", "pageProb": null, "wordConf": null}, {"leafNum": 15, "confidence": 100, "pageNumber": "5", "pageProb": 99, "wordConf": 24}, {"leafNum": 16, "confidence": null, "pageNumber": "6", "pageProb": null, "wordConf": null}, {"leafNum": 17, "confidence": 95, "pageNumber": "7", "pageProb": 85, "wordConf": 30}, {"leafNum": 18, "confidence": null, "pageNumber": "8", "pageProb": null, "wordConf": null}, {"leafNum": 19, "confidence": 100, "pageNumber": "9", "pageProb": 95, "wordConf": 28}, {"leafNum": 20, "confidence": null, "pageNumber": "10", "pageProb": null, "wordConf": null}, {"leafNum": 21, "confidence": null, "pageNumber": "11", "pageProb": null, "wordConf": null}, {"leafNum": 22, "confidence": null, "pageNumber": "12", "pageProb": null, "wordConf": null}, {"leafNum": 23, "confidence": 100, "pageNumber": "13", "pageProb": 98, "wordConf": 5}, {"leafNum": 24, "confidence": null, "pageNumber": "14", "pageProb": null, "wordConf": null}, {"leafNum": 25, "confidence": null, "pageNumber": "15", "pageProb": null, "wordConf": null}, {"leafNum": 26, "confidence": null, "pageNumber": "16", "pageProb": null, "wordConf": null}, {"leafNum": 27, "confidence": 100, "pageNumber": "17", "pageProb": 95, "wordConf": 6}, {"leafNum": 28, "confidence": null, "pageNumber": "18", "pageProb": null, "wordConf": null}, {"leafNum": 29, "confidence": 100, "pageNumber": "19", "pageProb": 99, "wordConf": 6}, {"leafNum": 30, "confidence": null, "pageNumber": "20", "pageProb": null, "wordConf": null}, {"leafNum": 31, "confidence": 100, "pageNumber": "21", "pageProb": 98, "wordConf": 6}, {"leafNum": 32, "confidence": null, "pageNumber": "22", "pageProb": null, "wordConf": null}, {"leafNum": 33, "confidence": 100, "pageNumber": "23", "pageProb": 93, "wordConf": 26}, {"leafNum": 34, "confidence": null, "pageNumber": "24", "pageProb": null, "wordConf": null}, {"leafNum": 35, "confidence": 100, "pageNumber": "25", "pageProb": 98, "wordConf": 24}, {"leafNum": 36, "confidence": null, "pageNumber": "26", "pageProb": null, "wordConf": null}, {"leafNum": 37, "confidence": 100, "pageNumber": "27", "pageProb": 98, "wordConf": 6}, {"leafNum": 38, "confidence": null, "pageNumber": "28", "pageProb": null, "wordConf": null}, {"leafNum": 39, "confidence": 100, "pageNumber": "29", "pageProb": 99, "wordConf": 29}, {"leafNum": 40, "confidence": null, "pageNumber": "30", "pageProb": null, "wordConf": null}, {"leafNum": 41, "confidence": null, "pageNumber": "31", "pageProb": null, "wordConf": null}, {"leafNum": 42, "confidence": null, "pageNumber": "32", "pageProb": null, "wordConf": null}, {"leafNum": 43, "confidence": 100, "pageNumber": "33", "pageProb": 98, "wordConf": 28}, {"leafNum": 44, "confidence": null, "pageNumber": "34", "pageProb": null, "wordConf": null}, {"leafNum": 45, "confidence": 100, "pageNumber": "35", "pageProb": 98, "wordConf": 22}, {"leafNum": 46, "confidence": null, "pageNumber": "36", "pageProb": null, "wordConf": null}, {"leafNum": 47, "confidence": 100, "pageNumber": "37", "pageProb": 93, "wordConf": 26}, {"leafNum": 48, "confidence": null, "pageNumber": "38", "pageProb": null, "wordConf": null}, {"leafNum": 49, "confidence": null, "pageNumber": "39", "pageProb": null, "wordConf": null}, {"leafNum": 50, "confidence": null, "pageNumber": "40", "pageProb": null, "wordConf": null}, {"leafNum": 51, "confidence": null, "pageNumber": "41", "pageProb": null, "wordConf": null}, {"leafNum": 52, "confidence": null, "pageNumber": "42", "pageProb": null, "wordConf": null}, {"leafNum": 53, "confidence": null, "pageNumber": "43", "pageProb": null, "wordConf": null}, {"leafNum": 54, "confidence": null, "pageNumber": "44", "pageProb": null, "wordConf": null}, {"leafNum": 55, "confidence": 100, "pageNumber": "45", "pageProb": 98, "wordConf": 29}, {"leafNum": 56, "confidence": null, "pageNumber": "46", "pageProb": null, "wordConf": null}, {"leafNum": 57, "confidence": 100, "pageNumber": "47", "pageProb": 98, "wordConf": 27}, {"leafNum": 58, "confidence": null, "pageNumber": "48", "pageProb": null, "wordConf": null}, {"leafNum": 59, "confidence": 100, "pageNumber": "49", "pageProb": 99, "wordConf": 20}, {"leafNum": 60, "confidence": null, "pageNumber": "50", "pageProb": null, "wordConf": null}, {"leafNum": 61, "confidence": null, "pageNumber": "51", "pageProb": null, "wordConf": null}, {"leafNum": 62, "confidence": null, "pageNumber": "52", "pageProb": null, "wordConf": null}, {"leafNum": 63, "confidence": 100, "pageNumber": "53", "pageProb": 99, "wordConf": 3}, {"leafNum": 64, "confidence": null, "pageNumber": "54", "pageProb": null, "wordConf": null}, {"leafNum": 65, "confidence": 100, "pageNumber": "55", "pageProb": 98, "wordConf": 27}, {"leafNum": 66, "confidence": null, "pageNumber": "56", "pageProb": null, "wordConf": null}, {"leafNum": 67, "confidence": 100, "pageNumber": "57", "pageProb": 94, "wordConf": 28}, {"leafNum": 68, "confidence": null, "pageNumber": "58", "pageProb": null, "wordConf": null}, {"leafNum": 69, "confidence": 100, "pageNumber": "59", "pageProb": 98, "wordConf": 22}, {"leafNum": 70, "confidence": null, "pageNumber": "60", "pageProb": null, "wordConf": null}, {"leafNum": 71, "confidence": null, "pageNumber": "61", "pageProb": null, "wordConf": null}, {"leafNum": 72, "confidence": null, "pageNumber": "62", "pageProb": null, "wordConf": null}, {"leafNum": 73, "confidence": 100, "pageNumber": "63", "pageProb": 98, "wordConf": 6}, {"leafNum": 74, "confidence": null, "pageNumber": "64", "pageProb": null, "wordConf": null}, {"leafNum": 75, "confidence": null, "pageNumber": "65", "pageProb": null, "wordConf": null}, {"leafNum": 76, "confidence": null, "pageNumber": "66", "pageProb": null, "wordConf": null}, {"leafNum": 77, "confidence": null, "pageNumber": "67", "pageProb": null, "wordConf": null}, {"leafNum": 78, "confidence": null, "pageNumber": "68", "pageProb": null, "wordConf": null}, {"leafNum": 79, "confidence": 100, "pageNumber": "69", "pageProb": 93, "wordConf": 29}, {"leafNum": 80, "confidence": null, "pageNumber": "70", "pageProb": null, "wordConf": null}, {"leafNum": 81, "confidence": null, "pageNumber": "71", "pageProb": null, "wordConf": null}, {"leafNum": 82, "confidence": null, "pageNumber": "72", "pageProb": null, "wordConf": null}, {"leafNum": 83, "confidence": 100, "pageNumber": "73", "pageProb": 98, "wordConf": 23}, {"leafNum": 84, "confidence": null, "pageNumber": "74", "pageProb": null, "wordConf": null}, {"leafNum": 85, "confidence": null, "pageNumber": "75", "pageProb": null, "wordConf": null}, {"leafNum": 86, "confidence": null, "pageNumber": "76", "pageProb": null, "wordConf": null}, {"leafNum": 87, "confidence": 100, "pageNumber": "77", "pageProb": 94, "wordConf": 2}, {"leafNum": 88, "confidence": null, "pageNumber": "78", "pageProb": null, "wordConf": null}, {"leafNum": 89, "confidence": 100, "pageNumber": "79", "pageProb": 99, "wordConf": 22}, {"leafNum": 90, "confidence": null, "pageNumber": "80", "pageProb": null, "wordConf": null}, {"leafNum": 91, "confidence": null, "pageNumber": "81", "pageProb": null, "wordConf": null}, {"leafNum": 92, "confidence": null, "pageNumber": "82", "pageProb": null, "wordConf": null}, {"leafNum": 93, "confidence": null, "pageNumber": "83", "pageProb": null, "wordConf": null}, {"leafNum": 94, "confidence": null, "pageNumber": "84", "pageProb": null, "wordConf": null}, {"leafNum": 95, "confidence": null, "pageNumber": "85", "pageProb": null, "wordConf": null}, {"leafNum": 96, "confidence": null, "pageNumber": "86", "pageProb": null, "wordConf": null}, {"leafNum": 97, "confidence": 100, "pageNumber": "87", "pageProb": 98, "wordConf": 27}, {"leafNum": 98, "confidence": null, "pageNumber": "88", "pageProb": null, "wordConf": null}, {"leafNum": 99, "confidence": 100, "pageNumber": "89", "pageProb": 99, "wordConf": 25}, {"leafNum": 100, "confidence": null, "pageNumber": "90", "pageProb": null, "wordConf": null}, {"leafNum": 101, "confidence": 100, "pageNumber": "91", "pageProb": 98, "wordConf": 6}, {"leafNum": 102, "confidence": null, "pageNumber": "92", "pageProb": null, "wordConf": null}, {"leafNum": 103, "confidence": 100, "pageNumber": "93", "pageProb": 93, "wordConf": 6}, {"leafNum": 104, "confidence": null, "pageNumber": "94", "pageProb": null, "wordConf": null}, {"leafNum": 105, "confidence": 100, "pageNumber": "95", "pageProb": 98, "wordConf": 28}, {"leafNum": 106, "confidence": null, "pageNumber": "96", "pageProb": null, "wordConf": null}, {"leafNum": 107, "confidence": 100, "pageNumber": "97", "pageProb": 98, "wordConf": 28}, {"leafNum": 108, "confidence": null, "pageNumber": "98", "pageProb": null, "wordConf": null}, {"leafNum": 109, "confidence": 100, "pageNumber": "99", "pageProb": 98, "wordConf": 28}, {"leafNum": 110, "confidence": null, "pageNumber": "100", "pageProb": null, "wordConf": null}, {"leafNum": 111, "confidence": null, "pageNumber": "101", "pageProb": null, "wordConf": null}, {"leafNum": 112, "confidence": null, "pageNumber": "102", "pageProb": null, "wordConf": null}, {"leafNum": 113, "confidence": null, "pageNumber": "103", "pageProb": null, "wordConf": null}, {"leafNum": 114, "confidence": null, "pageNumber": "104", "pageProb": null, "wordConf": null}, {"leafNum": 115, "confidence": 100, "pageNumber": "105", "pageProb": 98, "wordConf": 12}, {"leafNum": 116, "confidence": null, "pageNumber": "106", "pageProb": null, "wordConf": null}, {"leafNum": 117, "confidence": null, "pageNumber": "107", "pageProb": null, "wordConf": null}, {"leafNum": 118, "confidence": null, "pageNumber": "108", "pageProb": null, "wordConf": null}, {"leafNum": 119, "confidence": 99, "pageNumber": "109", "pageProb": 89, "wordConf": 24}, {"leafNum": 120, "confidence": null, "pageNumber": "110", "pageProb": null, "wordConf": null}, {"leafNum": 121, "confidence": null, "pageNumber": "111", "pageProb": null, "wordConf": null}, {"leafNum": 122, "confidence": null, "pageNumber": "112", "pageProb": null, "wordConf": null}, {"leafNum": 123, "confidence": 98, "pageNumber": "113", "pageProb": 88, "wordConf": 3}, {"leafNum": 124, "confidence": null, "pageNumber": "114", "pageProb": null, "wordConf": null}, {"leafNum": 125, "confidence": null, "pageNumber": "115", "pageProb": null, "wordConf": null}, {"leafNum": 126, "confidence": null, "pageNumber": "116", "pageProb": null, "wordConf": null}, {"leafNum": 127, "confidence": null, "pageNumber": "117", "pageProb": null, "wordConf": null}, {"leafNum": 128, "confidence": null, "pageNumber": "118", "pageProb": null, "wordConf": null}, {"leafNum": 129, "confidence": 99, "pageNumber": "119", "pageProb": 89, "wordConf": 3}, {"leafNum": 130, "confidence": null, "pageNumber": "120", "pageProb": null, "wordConf": null}, {"leafNum": 131, "confidence": 100, "pageNumber": "121", "pageProb": 98, "wordConf": 3}, {"leafNum": 132, "confidence": null, "pageNumber": "122", "pageProb": null, "wordConf": null}, {"leafNum": 133, "confidence": null, "pageNumber": "123", "pageProb": null, "wordConf": null}, {"leafNum": 134, "confidence": null, "pageNumber": "124", "pageProb": null, "wordConf": null}, {"leafNum": 135, "confidence": null, "pageNumber": "125", "pageProb": null, "wordConf": null}, {"leafNum": 136, "confidence": null, "pageNumber": "126", "pageProb": null, "wordConf": null}, {"leafNum": 137, "confidence": 100, "pageNumber": "127", "pageProb": 91, "wordConf": 13}, {"leafNum": 138, "confidence": null, "pageNumber": "128", "pageProb": null, "wordConf": null}, {"leafNum": 139, "confidence": 100, "pageNumber": "129", "pageProb": 98, "wordConf": 12}, {"leafNum": 140, "confidence": null, "pageNumber": "130", "pageProb": null, "wordConf": null}, {"leafNum": 141, "confidence": null, "pageNumber": "131", "pageProb": null, "wordConf": null}, {"leafNum": 142, "confidence": null, "pageNumber": "132", "pageProb": null, "wordConf": null}, {"leafNum": 143, "confidence": 100, "pageNumber": "133", "pageProb": 99, "wordConf": 11}, {"leafNum": 144, "confidence": null, "pageNumber": "134", "pageProb": null, "wordConf": null}, {"leafNum": 145, "confidence": 98, "pageNumber": "135", "pageProb": 88, "wordConf": 11}, {"leafNum": 146, "confidence": null, "pageNumber": "136", "pageProb": null, "wordConf": null}, {"leafNum": 147, "confidence": null, "pageNumber": "137", "pageProb": null, "wordConf": null}, {"leafNum": 148, "confidence": null, "pageNumber": "138", "pageProb": null, "wordConf": null}, {"leafNum": 149, "confidence": 100, "pageNumber": "139", "pageProb": 98, "wordConf": 2}, {"leafNum": 150, "confidence": null, "pageNumber": "140", "pageProb": null, "wordConf": null}, {"leafNum": 151, "confidence": null, "pageNumber": "141", "pageProb": null, "wordConf": null}, {"leafNum": 152, "confidence": null, "pageNumber": "142", "pageProb": null, "wordConf": null}, {"leafNum": 153, "confidence": 100, "pageNumber": "143", "pageProb": 98, "wordConf": 11}, {"leafNum": 154, "confidence": null, "pageNumber": "144", "pageProb": null, "wordConf": null}, {"leafNum": 155, "confidence": null, "pageNumber": "145", "pageProb": null, "wordConf": null}, {"leafNum": 156, "confidence": null, "pageNumber": "146", "pageProb": null, "wordConf": null}, {"leafNum": 157, "confidence": 98, "pageNumber": "147", "pageProb": 88, "wordConf": 10}, {"leafNum": 158, "confidence": null, "pageNumber": "148", "pageProb": null, "wordConf": null}, {"leafNum": 159, "confidence": 98, "pageNumber": "149", "pageProb": 88, "wordConf": 12}, {"leafNum": 160, "confidence": null, "pageNumber": "150", "pageProb": null, "wordConf": null}, {"leafNum": 161, "confidence": null, "pageNumber": "151", "pageProb": null, "wordConf": null}, {"leafNum": 162, "confidence": null, "pageNumber": "152", "pageProb": null, "wordConf": null}, {"leafNum": 163, "confidence": 98, "pageNumber": "153", "pageProb": 88, "wordConf": 12}, {"leafNum": 164, "confidence": null, "pageNumber": "154", "pageProb": null, "wordConf": null}, {"leafNum": 165, "confidence": null, "pageNumber": "155", "pageProb": null, "wordConf": null}, {"leafNum": 166, "confidence": null, "pageNumber": "156", "pageProb": null, "wordConf": null}, {"leafNum": 167, "confidence": 100, "pageNumber": "157", "pageProb": 98, "wordConf": 9}, {"leafNum": 168, "confidence": null, "pageNumber": "158", "pageProb": null, "wordConf": null}, {"leafNum": 169, "confidence": 100, "pageNumber": "159", "pageProb": 92, "wordConf": 2}, {"leafNum": 170, "confidence": null, "pageNumber": "160", "pageProb": null, "wordConf": null}, {"leafNum": 171, "confidence": null, "pageNumber": "161", "pageProb": null, "wordConf": null}, {"leafNum": 172, "confidence": null, "pageNumber": "162", "pageProb": null, "wordConf": null}, {"leafNum": 173, "confidence": null, "pageNumber": "163", "pageProb": null, "wordConf": null}, {"leafNum": 174, "confidence": null, "pageNumber": "164", "pageProb": null, "wordConf": null}, {"leafNum": 175, "confidence": 100, "pageNumber": "165", "pageProb": 97, "wordConf": 2}, {"leafNum": 176, "confidence": null, "pageNumber": "166", "pageProb": null, "wordConf": null}, {"leafNum": 177, "confidence": 100, "pageNumber": "167", "pageProb": 98, "wordConf": 12}, {"leafNum": 178, "confidence": null, "pageNumber": "168", "pageProb": null, "wordConf": null}, {"leafNum": 179, "confidence": 100, "pageNumber": "169", "pageProb": 98, "wordConf": 28}, {"leafNum": 180, "confidence": null, "pageNumber": "170", "pageProb": null, "wordConf": null}, {"leafNum": 181, "confidence": null, "pageNumber": "171", "pageProb": null, "wordConf": null}, {"leafNum": 182, "confidence": null, "pageNumber": "172", "pageProb": null, "wordConf": null}, {"leafNum": 183, "confidence": null, "pageNumber": "173", "pageProb": null, "wordConf": null}, {"leafNum": 184, "confidence": null, "pageNumber": "174", "pageProb": null, "wordConf": null}, {"leafNum": 185, "confidence": 100, "pageNumber": "175", "pageProb": 93, "wordConf": 12}, {"leafNum": 186, "confidence": null, "pageNumber": "176", "pageProb": null, "wordConf": null}, {"leafNum": 187, "confidence": 100, "pageNumber": "177", "pageProb": 90, "wordConf": 2}, {"leafNum": 188, "confidence": null, "pageNumber": "178", "pageProb": null, "wordConf": null}, {"leafNum": 189, "confidence": null, "pageNumber": "179", "pageProb": null, "wordConf": null}, {"leafNum": 190, "confidence": null, "pageNumber": "180", "pageProb": null, "wordConf": null}, {"leafNum": 191, "confidence": null, "pageNumber": "181", "pageProb": null, "wordConf": null}, {"leafNum": 192, "confidence": null, "pageNumber": "182", "pageProb": null, "wordConf": null}, {"leafNum": 193, "confidence": null, "pageNumber": "183", "pageProb": null, "wordConf": null}, {"leafNum": 194, "confidence": null, "pageNumber": "184", "pageProb": null, "wordConf": null}, {"leafNum": 195, "confidence": 100, "pageNumber": "185", "pageProb": 90, "wordConf": 11}, {"leafNum": 196, "confidence": null, "pageNumber": "186", "pageProb": null, "wordConf": null}, {"leafNum": 197, "confidence": 100, "pageNumber": "187", "pageProb": 92, "wordConf": 2}, {"leafNum": 198, "confidence": null, "pageNumber": "188", "pageProb": null, "wordConf": null}, {"leafNum": 199, "confidence": 100, "pageNumber": "189", "pageProb": 91, "wordConf": 13}, {"leafNum": 200, "confidence": null, "pageNumber": "190", "pageProb": null, "wordConf": null}, {"leafNum": 201, "confidence": null, "pageNumber": "191", "pageProb": null, "wordConf": null}, {"leafNum": 202, "confidence": null, "pageNumber": "192", "pageProb": null, "wordConf": null}, {"leafNum": 203, "confidence": null, "pageNumber": "193", "pageProb": null, "wordConf": null}, {"leafNum": 204, "confidence": null, "pageNumber": "194", "pageProb": null, "wordConf": null}, {"leafNum": 205, "confidence": null, "pageNumber": "195", "pageProb": null, "wordConf": null}, {"leafNum": 206, "confidence": null, "pageNumber": "196", "pageProb": null, "wordConf": null}, {"leafNum": 207, "confidence": 100, "pageNumber": "197", "pageProb": 90, "wordConf": 2}, {"leafNum": 208, "confidence": null, "pageNumber": "198", "pageProb": null, "wordConf": null}, {"leafNum": 209, "confidence": 94, "pageNumber": "199", "pageProb": 84, "wordConf": 13}, {"leafNum": 210, "confidence": null, "pageNumber": "200", "pageProb": null, "wordConf": null}, {"leafNum": 211, "confidence": null, "pageNumber": "201", "pageProb": null, "wordConf": null}, {"leafNum": 212, "confidence": null, "pageNumber": "202", "pageProb": null, "wordConf": null}, {"leafNum": 213, "confidence": null, "pageNumber": "203", "pageProb": null, "wordConf": null}, {"leafNum": 214, "confidence": null, "pageNumber": "204", "pageProb": null, "wordConf": null}, {"leafNum": 215, "confidence": 98, "pageNumber": "205", "pageProb": 88, "wordConf": 9}, {"leafNum": 216, "confidence": null, "pageNumber": "206", "pageProb": null, "wordConf": null}, {"leafNum": 217, "confidence": null, "pageNumber": "207", "pageProb": null, "wordConf": null}, {"leafNum": 218, "confidence": null, "pageNumber": "208", "pageProb": null, "wordConf": null}, {"leafNum": 219, "confidence": null, "pageNumber": "209", "pageProb": null, "wordConf": null}, {"leafNum": 220, "confidence": null, "pageNumber": "210", "pageProb": null, "wordConf": null}, {"leafNum": 221, "confidence": 100, "pageNumber": "211", "pageProb": 91, "wordConf": 3}, {"leafNum": 222, "confidence": null, "pageNumber": "212", "pageProb": null, "wordConf": null}, {"leafNum": 223, "confidence": null, "pageNumber": "213", "pageProb": null, "wordConf": null}, {"leafNum": 224, "confidence": null, "pageNumber": "214", "pageProb": null, "wordConf": null}, {"leafNum": 225, "confidence": 95, "pageNumber": "215", "pageProb": 85, "wordConf": 12}, {"leafNum": 226, "confidence": null, "pageNumber": "216", "pageProb": null, "wordConf": null}, {"leafNum": 227, "confidence": 95, "pageNumber": "217", "pageProb": 85, "wordConf": 12}, {"leafNum": 228, "confidence": null, "pageNumber": "218", "pageProb": null, "wordConf": null}, {"leafNum": 229, "confidence": null, "pageNumber": "219", "pageProb": null, "wordConf": null}, {"leafNum": 230, "confidence": null, "pageNumber": "220", "pageProb": null, "wordConf": null}, {"leafNum": 231, "confidence": 100, "pageNumber": "221", "pageProb": 90, "wordConf": 12}, {"leafNum": 232, "confidence": null, "pageNumber": "222", "pageProb": null, "wordConf": null}, {"leafNum": 233, "confidence": null, "pageNumber": "223", "pageProb": null, "wordConf": null}, {"leafNum": 234, "confidence": null, "pageNumber": "224", "pageProb": null, "wordConf": null}, {"leafNum": 235, "confidence": null, "pageNumber": "225", "pageProb": null, "wordConf": null}, {"leafNum": 236, "confidence": null, "pageNumber": "226", "pageProb": null, "wordConf": null}, {"leafNum": 237, "confidence": null, "pageNumber": "227", "pageProb": null, "wordConf": null}, {"leafNum": 238, "confidence": null, "pageNumber": "228", "pageProb": null, "wordConf": null}, {"leafNum": 239, "confidence": 100, "pageNumber": "229", "pageProb": 97, "wordConf": 25}, {"leafNum": 240, "confidence": null, "pageNumber": "", "pageProb": null, "wordConf": null}, {"leafNum": 241, "confidence": null, "pageNumber": "", "pageProb": null, "wordConf": null}, {"leafNum": 242, "confidence": null, "pageNumber": "", "pageProb": null, "wordConf": null}, {"leafNum": 243, "confidence": null, "pageNumber": "", "pageProb": null, "wordConf": null}, {"leafNum": 244, "confidence": null, "pageNumber": "", "pageProb": null, "wordConf": null}, {"leafNum": 245, "confidence": null, "pageNumber": "", "pageProb": null, "wordConf": null}, {"leafNum": 246, "confidence": null, "pageNumber": "", "pageProb": null, "wordConf": null}]}, "server": "ia800907.us.archive.org", "servers_unavailable": true, "uniq": 1058186972, "workable_servers": ["ia800907.us.archive.org"]}
